Workbook

Sheet Customer Names
A1: =PROPER("Customer ID") -> Customer Id | B1: Title | C1: First Name | D1: Last Name
A2: Id1 | B2: Hawks, Ms. Kelly | C2: =LEFT(B2,FIND(" ",B2)-2) -> Hawks | D2: =RIGHT(B2,LEN(B2)-FIND(" ",B2)) -> Kelly
A3: Id2 | B3: Lehner, Mr. Matthew D | C3: =LEFT(B3,FIND(" ",B3)-2) -> Lehner | D3: =RIGHT(B3,LEN(B3)-FIND(" ",B3)) -> Matthew D
A4: Id3 | B4: Lu, Mr. Phil | C4: =LEFT(B4,FIND(" ",B4)-2) -> Lu | D4: =RIGHT(B4,LEN(B4)-FIND(" ",B4)) -> Phil
A5: Id4 | B5: Osborne, Ms. Kelsey | C5: =LEFT(B5,FIND(" ",B5)-2) -> Osborne | D5: =RIGHT(B5,LEN(B5)-FIND(" ",B5)) -> Kelsey
A6: Id5 | B6: Kadala, Ms. Kristyn | C6: =LEFT(B6,FIND(" ",B6)-2) -> Kadala | D6: =RIGHT(B6,LEN(B6)-FIND(" ",B6)) -> Kristyn
A7: Id6 | B7: Baker, Mr. Russell B. | C7: =LEFT(B7,FIND(" ",B7)-2) -> Baker | D7: =RIGHT(B7,LEN(B7)-FIND(" ",B7)) -> Russell B.
A8: Id7 | B8: Macpherson, Mr. Scott | C8: =LEFT(B8,FIND(" ",B8)-2) -> Macpherson | D8: =RIGHT(B8,LEN(B8)-FIND(" ",B8)) -> Scott
A9: Id8 | B9: Hallman, Mr. Stephen | C9: =LEFT(B9,FIND(" ",B9)-2) -> Hallman | D9: =RIGHT(B9,LEN(B9)-FIND(" ",B9)) -> Stephen
A10: Id9 | B10: Moran, Mr. Patrick R. | C10: =LEFT(B10,FIND(" ",B10)-2) -> Moran | D10: =RIGHT(B10,LEN(B10)-FIND(" ",B10)) -> Patrick R.
A11: Id10 | B11: Benner, Ms. Brooke N. | C11: =LEFT(B11,FIND(" ",B11)-2) -> Benner | D11: =RIGHT(B11,LEN(B11)-FIND(" ",B11)) -> Brooke N.
A12: Id11 | B12: Fierro Vargas, Ms. Paola Andrea | C12: =LEFT(B12,FIND(" ",B12)-2) -> Fierr | D12: =RIGHT(B12,LEN(B12)-FIND(" ",B12)) -> Paola Andrea
A13: Id12 | B13: Franz, Mr. David | C13: =LEFT(B13,FIND(" ",B13)-2) -> Franz | D13: =RIGHT(B13,LEN(B13)-FIND(" ",B13)) -> David
... A2336: Id2335 | B2336: German, Mr. Aaron K | C2336: =LEFT(B2336,FIND(" ",B2336)-2) -> German | D2336: =RIGHT(B2336,LEN(B2336)-FIND(" ",B2336)) -> Aaron K

Sheet Medical Examinations
A1: Customer Id | B1: BMI | C1: HBA1C | D1: Heart Issues | E1: Any Transplants | F1: Cancer history | G1: NumberOfMajorSurgeries | H1: smoker | I1: SMOKER | J1: NO.OF.MAJOR SURGERIES | K1: WEIGHT STATUS
A2: Id1 | B2: 47.41 | C2: 7.47 | D2: No | E2: No | F2: No | G2: No major surgery | H2: Yes | I2: =IF(H2="?",$H$2,H2) -> Yes | J2: =IF(G2="No major surgery",0,G2) -> 0 | K2: =IF(B2<18.5,"UNDERWEIGHT",IF(B2<25,"NORMAL WEIGHT",IF(B2<29.9,"OVERWEIGHT","OBESITY"))) -> OBESITY | M2: NO. OF "?' IN CUSTOMER Id COLUMN | N2: COUNTIF | O2: =COUNTIF(A2:A2336,"?") -> 0
A3: Id2 | B3: 30.36 | C3: 5.77 | D3: No | E3: No | F3: No | G3: No major surgery | H3: Yes | I3: =IF(H3="?",$H$2,H3) -> Yes | J3: =IF(G3="No major surgery",0,G3) -> 0 | K3: =IF(B3<18.5,"UNDERWEIGHT",IF(B3<25,"NORMAL WEIGHT",IF(B3<29.9,"OVERWEIGHT","OBESITY"))) -> OBESITY | M3: NO.OF "?" IN BMI COLUMN | N3: COUNTIF | O3: =COUNTIF(B2:B2336,"?") -> 0
A4: Id3 | B4: 34.485 | C4: 11.87 | D4: Yes | E4: No | F4: No | G4: 2 | H4: Yes | I4: =IF(H4="?",$H$2,H4) -> Yes | J4: =IF(G4="No major surgery",0,G4) -> 2 | K4: =IF(B4<18.5,"UNDERWEIGHT",IF(B4<25,"NORMAL WEIGHT",IF(B4<29.9,"OVERWEIGHT","OBESITY"))) -> OBESITY | M4: NO.OF "?" IN HBA1C COLUMN | N4: COUNTIF | O4: =COUNTIF(C2:C2336,"?") -> 0
A5: Id4 | B5: 38.095 | C5: 6.05 | D5: No | E5: No | F5: No | G5: No major surgery | H5: Yes | I5: =IF(H5="?",$H$2,H5) -> Yes | J5: =IF(G5="No major surgery",0,G5) -> 0 | K5: =IF(B5<18.5,"UNDERWEIGHT",IF(B5<25,"NORMAL WEIGHT",IF(B5<29.9,"OVERWEIGHT","OBESITY"))) -> OBESITY | M5: NO.OF "?" IN HEART ISSUE COLUMN | N5: COUNTIF | O5: =COUNTIF(D2:D2336,"?") -> 0
A6: Id5 | B6: 35.53 | C6: 5.45 | D6: No | E6: No | F6: No | G6: No major surgery | H6: Yes | I6: =IF(H6="?",$H$2,H6) -> Yes | J6: =IF(G6="No major surgery",0,G6) -> 0 | K6: =IF(B6<18.5,"UNDERWEIGHT",IF(B6<25,"NORMAL WEIGHT",IF(B6<29.9,"OVERWEIGHT","OBESITY"))) -> OBESITY | M6: NO.OF "?" IN ANY TRANSPLANT COLUMN | N6: COUNTIF | O6: =COUNTIF(E2:E2336,"?") -> 0
A7: Id6 | B7: 32.8 | C7: 6.59 | D7: No | E7: No | F7: No | G7: No major surgery | H7: Yes | I7: =IF(H7="?",$H$2,H7) -> Yes | J7: =IF(G7="No major surgery",0,G7) -> 0 | K7: =IF(B7<18.5,"UNDERWEIGHT",IF(B7<25,"NORMAL WEIGHT",IF(B7<29.9,"OVERWEIGHT","OBESITY"))) -> OBESITY | M7: NO.OF "?" IN CANCER HISTORY COLUMN | N7: COUNTIF | O7: =COUNTIF(F2:F2336,"?") -> 0
A8: Id7 | B8: 36.4 | C8: 6.07 | D8: No | E8: No | F8: No | G8: No major surgery | H8: Yes | I8: =IF(H8="?",$H$2,H8) -> Yes | J8: =IF(G8="No major surgery",0,G8) -> 0 | K8: =IF(B8<18.5,"UNDERWEIGHT",IF(B8<25,"NORMAL WEIGHT",IF(B8<29.9,"OVERWEIGHT","OBESITY"))) -> OBESITY | M8: NO.OF "?" IN MAJOR SURGERIES COLUMN | N8: COUNTIF | O8: =COUNTIF(G2:G2336,"?") -> 0
A9: Id8 | B9: 36.96 | C9: 7.93 | D9: No | E9: No | F9: No | G9: 3 | H9: Yes | I9: =IF(H9="?",$H$2,H9) -> Yes | J9: =IF(G9="No major surgery",0,G9) -> 3 | K9: =IF(B9<18.5,"UNDERWEIGHT",IF(B9<25,"NORMAL WEIGHT",IF(B9<29.9,"OVERWEIGHT","OBESITY"))) -> OBESITY | M9: NO.OF "?" IN SMOKER TIERCOLUMN | N9: COUNTIF | O9: =COUNTIF(H2:H2336,"?") -> 2
A10: Id9 | B10: 41.14 | C10: 9.58 | D10: Yes | E10: No | F10: Yes | G10: 1 | H10: Yes | I10: =IF(H10="?",$H$2,H10) -> Yes | J10: =IF(G10="No major surgery",0,G10) -> 1 | K10: =IF(B10<18.5,"UNDERWEIGHT",IF(B10<25,"NORMAL WEIGHT",IF(B10<29.9,"OVERWEIGHT","OBESITY"))) -> OBESITY | N10: TOTAL | O10: =SUM(O2:O9) -> 2
A11: Id10 | B11: 38.06 | C11: 10.79 | D11: No | E11: No | F11: No | G11: No major surgery | H11: Yes | I11: =IF(H11="?",$H$2,H11) -> Yes | J11: =IF(G11="No major surgery",0,G11) -> 0 | K11: =IF(B11<18.5,"UNDERWEIGHT",IF(B11<25,"NORMAL WEIGHT",IF(B11<29.9,"OVERWEIGHT","OBESITY"))) -> OBESITY
A12: Id11 | B12: 37.7 | C12: 5.96 | D12: Yes | E12: No | F12: No | G12: 2 | H12: Yes | I12: =IF(H12="?",$H$2,H12) -> Yes | J12: =IF(G12="No major surgery",0,G12) -> 2 | K12: =IF(B12<18.5,"UNDERWEIGHT",IF(B12<25,"NORMAL WEIGHT",IF(B12<29.9,"OVERWEIGHT","OBESITY"))) -> OBESITY
A13: Id12 | B13: 42.13 | C13: 11.9 | D13: No | E13: No | F13: No | G13: No major surgery | H13: Yes | I13: =IF(H13="?",$H$2,H13) -> Yes | J13: =IF(G13="No major surgery",0,G13) -> 0 | K13: =IF(B13<18.5,"UNDERWEIGHT",IF(B13<25,"NORMAL WEIGHT",IF(B13<29.9,"OVERWEIGHT","OBESITY"))) -> OBESITY
A14: Id13 | B14: 40.92 | C14: 8.41 | D14: No | E14: No | F14: No | G14: No major surgery | H14: Yes | I14: =IF(H14="?",$H$2,H14) -> Yes | J14: =IF(G14="No major surgery",0,G14) -> 0 | K14: =IF(B14<18.5,"UNDERWEIGHT",IF(B14<25,"NORMAL WEIGHT",IF(B14<29.9,"OVERWEIGHT","OBESITY"))) -> OBESITY | M14: NO. OF SMOKER IS "Yes" | N14: COUNTIF | O14: =COUNTIF(I2:I2336,"Yes") -> 490
A15: Id14 | B15: 40.565 | C15: 7.02 | D15: No | E15: No | F15: No | G15: No major surgery | H15: Yes | I15: =IF(H15="?",$H$2,H15) -> Yes | J15: =IF(G15="No major surgery",0,G15) -> 0 | K15: =IF(B15<18.5,"UNDERWEIGHT",IF(B15<25,"NORMAL WEIGHT",IF(B15<29.9,"OVERWEIGHT","OBESITY"))) -> OBESITY | M15: NO. OF SMOKER IS" NO" | N15: COUNTIF | O15: =COUNTIF(I2:I2366,"no") -> 1845
A16: Id15 | B16: 36.385 | C16: 7.59 | D16: Yes | E16: No | F16: No | G16: 2 | H16: Yes | I16: =IF(H16="?",$H$2,H16) -> Yes | J16: =IF(G16="No major surgery",0,G16) -> 2 | K16: =IF(B16<18.5,"UNDERWEIGHT",IF(B16<25,"NORMAL WEIGHT",IF(B16<29.9,"OVERWEIGHT","OBESITY"))) -> OBESITY
A17: Id16 | B17: 39.9 | C17: 11.32 | D17: No | E17: No | F17: No | G17: No major surgery | H17: Yes | I17: =IF(H17="?",$H$2,H17) -> Yes | J17: =IF(G17="No major surgery",0,G17) -> 0 | K17: =IF(B17<18.5,"UNDERWEIGHT",IF(B17<25,"NORMAL WEIGHT",IF(B17<29.9,"OVERWEIGHT","OBESITY"))) -> OBESITY
A18: Id17 | B18: 33.8 | C18: 7.67 | D18: No | E18: No | F18: No | G18: 3 | H18: Yes | I18: =IF(H18="?",$H$2,H18) -> Yes | J18: =IF(G18="No major surgery",0,G18) -> 3 | K18: =IF(B18<18.5,"UNDERWEIGHT",IF(B18<25,"NORMAL WEIGHT",IF(B18<29.9,"OVERWEIGHT","OBESITY"))) -> OBESITY
A19: Id18 | B19: 36.765 | C19: 7.29 | D19: Yes | E19: No | F19: Yes | G19: 1 | H19: Yes | I19: =IF(H19="?",$H$2,H19) -> Yes | J19: =IF(G19="No major surgery",0,G19) -> 1 | K19: =IF(B19<18.5,"UNDERWEIGHT",IF(B19<25,"NORMAL WEIGHT",IF(B19<29.9,"OVERWEIGHT","OBESITY"))) -> OBESITY
A20: Id19 | B20: 36.955 | C20: 4.72 | D20: Yes | E20: No | F20: No | G20: 1 | H20: Yes | I20: =IF(H20="?",$H$2,H20) -> Yes | J20: =IF(G20="No major surgery",0,G20) -> 1 | K20: =IF(B20<18.5,"UNDERWEIGHT",IF(B20<25,"NORMAL WEIGHT",IF(B20<29.9,"OVERWEIGHT","OBESITY"))) -> OBESITY
A21: Id20 | B21: 42.9 | C21: 11.41 | D21: No | E21: No | F21: No | G21: No major surgery | H21: Yes | I21: =IF(H21="?",$H$2,H21) -> Yes | J21: =IF(G21="No major surgery",0,G21) -> 0 | K21: =IF(B21<18.5,"UNDERWEIGHT",IF(B21<25,"NORMAL WEIGHT",IF(B21<29.9,"OVERWEIGHT","OBESITY"))) -> OBESITY
A22: Id21 | B22: 36.3 | C22: 11.5 | D22: Yes | E22: No | F22: No | G22: 2 | H22: Yes | I22: =IF(H22="?",$H$2,H22) -> Yes | J22: =IF(G22="No major surgery",0,G22) -> 2 | K22: =IF(B22<18.5,"UNDERWEIGHT",IF(B22<25,"NORMAL WEIGHT",IF(B22<29.9,"OVERWEIGHT","OBESITY"))) -> OBESITY
A23: Id22 | B23: 32.2 | C23: 6.22 | D23: Yes | E23: No | F23: No | G23: 2 | H23: Yes | I23: =IF(H23="?",$H$2,H23) -> Yes | J23: =IF(G23="No major surgery",0,G23) -> 2 | K23: =IF(B23<18.5,"UNDERWEIGHT",IF(B23<25,"NORMAL WEIGHT",IF(B23<29.9,"OVERWEIGHT","OBESITY"))) -> OBESITY
A24: Id23 | B24: 31.3 | C24: 11.38 | D24: No | E24: No | F24: No | G24: 3 | H24: Yes | I24: =IF(H24="?",$H$2,H24) -> Yes | J24: =IF(G24="No major surgery",0,G24) -> 3 | K24: =IF(B24<18.5,"UNDERWEIGHT",IF(B24<25,"NORMAL WEIGHT",IF(B24<29.9,"OVERWEIGHT","OBESITY"))) -> OBESITY
A25: Id24 | B25: 41.8 | C25: 7.89 | D25: Yes | E25: No | F25: No | G25: 2 | H25: Yes | I25: =IF(H25="?",$H$2,H25) -> Yes | J25: =IF(G25="No major surgery",0,G25) -> 2 | K25: =IF(B25<18.5,"UNDERWEIGHT",IF(B25<25,"NORMAL WEIGHT",IF(B25<29.9,"OVERWEIGHT","OBESITY"))) -> OBESITY
A26: Id25 | B26: 35.09 | C26: 4.38 | D26: Yes | E26: No | F26: No | G26: 2 | H26: Yes | I26: =IF(H26="?",$H$2,H26) -> Yes | J26: =IF(G26="No major surgery",0,G26) -> 2 | K26: =IF(B26<18.5,"UNDERWEIGHT",IF(B26<25,"NORMAL WEIGHT",IF(B26<29.9,"OVERWEIGHT","OBESITY"))) -> OBESITY
A27: Id26 | B27: 33.88 | C27: 7.01 | D27: No | E27: No | F27: No | G27: 3 | H27: Yes | I27: =IF(H27="?",$H$2,H27) -> Yes | J27: =IF(G27="No major surgery",0,G27) -> 3 | K27: =IF(B27<18.5,"UNDERWEIGHT",IF(B27<25,"NORMAL WEIGHT",IF(B27<29.9,"OVERWEIGHT","OBESITY"))) -> OBESITY
A28: Id27 | B28: 30.875 | C28: 11.88 | D28: No | E28: No | F28: No | G28: No major surgery | H28: Yes | I28: =IF(H28="?",$H$2,H28) -> Yes | J28: =IF(G28="No major surgery",0,G28) -> 0 | K28: =IF(B28<18.5,"UNDERWEIGHT",IF(B28<25,"NORMAL WEIGHT",IF(B28<29.9,"OVERWEIGHT","OBESITY"))) -> OBESITY
A29: Id28 | B29: 36.86 | C29: 5.19 | D29: Yes | E29: No | F29: Yes | G29: 1 | H29: Yes | I29: =IF(H29="?",$H$2,H29) -> Yes | J29: =IF(G29="No major surgery",0,G29) -> 1 | K29: =IF(B29<18.5,"UNDERWEIGHT",IF(B29<25,"NORMAL WEIGHT",IF(B29<29.9,"OVERWEIGHT","OBESITY"))) -> OBESITY
A30: Id29 | B30: 35.86 | C30: 6.74 | D30: Yes | E30: No | F30: No | G30: 2 | H30: Yes | I30: =IF(H30="?",$H$2,H30) -> Yes | J30: =IF(G30="No major surgery",0,G30) -> 2 | K30: =IF(B30<18.5,"UNDERWEIGHT",IF(B30<25,"NORMAL WEIGHT",IF(B30<29.9,"OVERWEIGHT","OBESITY"))) -> OBESITY
A31: Id30 | B31: 37.05 | C31: 8.44 | D31: No | E31: No | F31: No | G31: No major surgery | H31: Yes | I31: =IF(H31="?",$H$2,H31) -> Yes | J31: =IF(G31="No major surgery",0,G31) -> 0 | K31: =IF(B31<18.5,"UNDERWEIGHT",IF(B31<25,"NORMAL WEIGHT",IF(B31<29.9,"OVERWEIGHT","OBESITY"))) -> OBESITY
A32: Id31 | B32: 43.89 | C32: 8.71 | D32: No | E32: No | F32: No | G32: No major surgery | H32: Yes | I32: =IF(H32="?",$H$2,H32) -> Yes | J32: =IF(G32="No major surgery",0,G32) -> 0 | K32: =IF(B32<18.5,"UNDERWEIGHT",IF(B32<25,"NORMAL WEIGHT",IF(B32<29.9,"OVERWEIGHT","OBESITY"))) -> OBESITY
A33: Id32 | B33: 42.35 | C33: 5.08 | D33: Yes | E33: No | F33: No | G33: No major surgery | H33: Yes | I33: =IF(H33="?",$H$2,H33) -> Yes | J33: =IF(G33="No major surgery",0,G33) -> 0 | K33: =IF(B33<18.5,"UNDERWEIGHT",IF(B33<25,"NORMAL WEIGHT",IF(B33<29.9,"OVERWEIGHT","OBESITY"))) -> OBESITY
A34: Id33 | B34: 31.35 | C34: 6.86 | D34: No | E34: No | F34: No | G34: No major surgery | H34: Yes | I34: =IF(H34="?",$H$2,H34) -> Yes | J34: =IF(G34="No major surgery",0,G34) -> 0 | K34: =IF(B34<18.5,"UNDERWEIGHT",IF(B34<25,"NORMAL WEIGHT",IF(B34<29.9,"OVERWEIGHT","OBESITY"))) -> OBESITY
A35: Id34 | B35: 47.6 | C35: 5.95 | D35: Yes | E35: No | F35: No | G35: No major surgery | H35: Yes | I35: =IF(H35="?",$H$2,H35) -> Yes | J35: =IF(G35="No major surgery",0,G35) -> 0 | K35: =IF(B35<18.5,"UNDERWEIGHT",IF(B35<25,"NORMAL WEIGHT",IF(B35<29.9,"OVERWEIGHT","OBESITY"))) -> OBESITY
A36: Id35 | B36: 46.2 | C36: 6.09 | D36: No | E36: No | F36: Yes | G36: 1 | H36: Yes | I36: =IF(H36="?",$H$2,H36) -> Yes | J36: =IF(G36="No major surgery",0,G36) -> 1 | K36: =IF(B36<18.5,"UNDERWEIGHT",IF(B36<25,"NORMAL WEIGHT",IF(B36<29.9,"OVERWEIGHT","OBESITY"))) -> OBESITY
A37: Id36 | B37: 32.015 | C37: 11.75 | D37: No | E37: No | F37: No | G37: No major surgery | H37: Yes | I37: =IF(H37="?",$H$2,H37) -> Yes | J37: =IF(G37="No major surgery",0,G37) -> 0 | K37: =IF(B37<18.5,"UNDERWEIGHT",IF(B37<25,"NORMAL WEIGHT",IF(B37<29.9,"OVERWEIGHT","OBESITY"))) -> OBESITY
A38: Id37 | B38: 40.565 | C38: 7.37 | D38: No | E38: No | F38: No | G38: No major surgery | H38: Yes | I38: =IF(H38="?",$H$2,H38) -> Yes | J38: =IF(G38="No major surgery",0,G38) -> 0 | K38: =IF(B38<18.5,"UNDERWEIGHT",IF(B38<25,"NORMAL WEIGHT",IF(B38<29.9,"OVERWEIGHT","OBESITY"))) -> OBESITY
A39: Id38 | B39: 32.45 | C39: 11.91 | D39: No | E39: No | F39: No | G39: No major surgery | H39: Yes | I39: =IF(H39="?",$H$2,H39) -> Yes | J39: =IF(G39="No major surgery",0,G39) -> 0 | K39: =IF(B39<18.5,"UNDERWEIGHT",IF(B39<25,"NORMAL WEIGHT",IF(B39<29.9,"OVERWEIGHT","OBESITY"))) -> OBESITY
A40: Id39 | B40: 34.96 | C40: 6.52 | D40: No | E40: No | F40: No | G40: No major surgery | H40: Yes | I40: =IF(H40="?",$H$2,H40) -> Yes | J40: =IF(G40="No major surgery",0,G40) -> 0 | K40: =IF(B40<18.5,"UNDERWEIGHT",IF(B40<25,"NORMAL WEIGHT",IF(B40<29.9,"OVERWEIGHT","OBESITY"))) -> OBESITY
A41: Id40 | B41: 35.5 | C41: 5.14 | D41: No | E41: No | F41: Yes | G41: 1 | H41: Yes | I41: =IF(H41="?",$H$2,H41) -> Yes | J41: =IF(G41="No major surgery",0,G41) -> 1 | K41: =IF(B41<18.5,"UNDERWEIGHT",IF(B41<25,"NORMAL WEIGHT",IF(B41<29.9,"OVERWEIGHT","OBESITY"))) -> OBESITY
A42: Id41 | B42: 52.58 | C42: 4.19 | D42: No | E42: Yes | F42: No | G42: 1 | H42: Yes | I42: =IF(H42="?",$H$2,H42) -> Yes | J42: =IF(G42="No major surgery",0,G42) -> 1 | K42: =IF(B42<18.5,"UNDERWEIGHT",IF(B42<25,"NORMAL WEIGHT",IF(B42<29.9,"OVERWEIGHT","OBESITY"))) -> OBESITY
A43: Id42 | B43: 35.2 | C43: 11.68 | D43: Yes | E43: No | F43: No | G43: No major surgery | H43: Yes | I43: =IF(H43="?",$H$2,H43) -> Yes | J43: =IF(G43="No major surgery",0,G43) -> 0 | K43: =IF(B43<18.5,"UNDERWEIGHT",IF(B43<25,"NORMAL WEIGHT",IF(B43<29.9,"OVERWEIGHT","OBESITY"))) -> OBESITY
A44: Id43 | B44: 38.06 | C44: 6.98 | D44: No | E44: No | F44: No | G44: No major surgery | H44: Yes | I44: =IF(H44="?",$H$2,H44) -> Yes | J44: =IF(G44="No major surgery",0,G44) -> 0 | K44: =IF(B44<18.5,"UNDERWEIGHT",IF(B44<25,"NORMAL WEIGHT",IF(B44<29.9,"OVERWEIGHT","OBESITY"))) -> OBESITY
A45: Id44 | B45: 34.21 | C45: 8.34 | D45: No | E45: No | F45: No | G45: No major surgery | H45: Yes | I45: =IF(H45="?",$H$2,H45) -> Yes | J45: =IF(G45="No major surgery",0,G45) -> 0 | K45: =IF(B45<18.5,"UNDERWEIGHT",IF(B45<25,"NORMAL WEIGHT",IF(B45<29.9,"OVERWEIGHT","OBESITY"))) -> OBESITY
A46: Id45 | B46: 38.94 | C46: 8.49 | D46: Yes | E46: No | F46: No | G46: 1 | H46: Yes | I46: =IF(H46="?",$H$2,H46) -> Yes | J46: =IF(G46="No major surgery",0,G46) -> 1 | K46: =IF(B46<18.5,"UNDERWEIGHT",IF(B46<25,"NORMAL WEIGHT",IF(B46<29.9,"OVERWEIGHT","OBESITY"))) -> OBESITY
A47: Id46 | B47: 30.21 | C47: 5.34 | D47: Yes | E47: No | F47: No | G47: 1 | H47: Yes | I47: =IF(H47="?",$H$2,H47) -> Yes | J47: =IF(G47="No major surgery",0,G47) -> 1 | K47: =IF(B47<18.5,"UNDERWEIGHT",IF(B47<25,"NORMAL WEIGHT",IF(B47<29.9,"OVERWEIGHT","OBESITY"))) -> OBESITY
A48: Id47 | B48: 33.63 | C48: 4.43 | D48: Yes | E48: No | F48: No | G48: 2 | H48: Yes | I48: =IF(H48="?",$H$2,H48) -> Yes | J48: =IF(G48="No major surgery",0,G48) -> 2 | K48: =IF(B48<18.5,"UNDERWEIGHT",IF(B48<25,"NORMAL WEIGHT",IF(B48<29.9,"OVERWEIGHT","OBESITY"))) -> OBESITY
A49: Id48 | B49: 40.37 | C49: 4.47 | D49: No | E49: No | F49: No | G49: No major surgery | H49: Yes | I49: =IF(H49="?",$H$2,H49) -> Yes | J49: =IF(G49="No major surgery",0,G49) -> 0 | K49: =IF(B49<18.5,"UNDERWEIGHT",IF(B49<25,"NORMAL WEIGHT",IF(B49<29.9,"OVERWEIGHT","OBESITY"))) -> OBESITY
A50: Id49 | B50: 53.09 | C50: 4.82 | D50: Yes | E50: No | F50: No | G50: 2 | H50: Yes | I50: =IF(H50="?",$H$2,H50) -> Yes | J50: =IF(G50="No major surgery",0,G50) -> 2 | K50: =IF(B50<18.5,"UNDERWEIGHT",IF(B50<25,"NORMAL WEIGHT",IF(B50<29.9,"OVERWEIGHT","OBESITY"))) -> OBESITY
A51: Id50 | B51: 31.79 | C51: 5.51 | D51: Yes | E51: No | F51: No | G51: 2 | H51: Yes | I51: =IF(H51="?",$H$2,H51) -> Yes | J51: =IF(G51="No major surgery",0,G51) -> 2 | K51: =IF(B51<18.5,"UNDERWEIGHT",IF(B51<25,"NORMAL WEIGHT",IF(B51<29.9,"OVERWEIGHT","OBESITY"))) -> OBESITY
A52: Id51 | B52: 41.895 | C52: 10.87 | D52: Yes | E52: No | F52: No | G52: 1 | H52: Yes | I52: =IF(H52="?",$H$2,H52) -> Yes | J52: =IF(G52="No major surgery",0,G52) -> 1 | K52: =IF(B52<18.5,"UNDERWEIGHT",IF(B52<25,"NORMAL WEIGHT",IF(B52<29.9,"OVERWEIGHT","OBESITY"))) -> OBESITY
A53: Id52 | B53: 31.16 | C53: 9.34 | D53: No | E53: No | F53: No | G53: No major surgery | H53: Yes | I53: =IF(H53="?",$H$2,H53) -> Yes | J53: =IF(G53="No major surgery",0,G53) -> 0 | K53: =IF(B53<18.5,"UNDERWEIGHT",IF(B53<25,"NORMAL WEIGHT",IF(B53<29.9,"OVERWEIGHT","OBESITY"))) -> OBESITY
A54: Id53 | B54: 34.105 | C54: 5.03 | D54: Yes | E54: No | F54: Yes | G54: 1 | H54: Yes | I54: =IF(H54="?",$H$2,H54) -> Yes | J54: =IF(G54="No major surgery",0,G54) -> 1 | K54: =IF(B54<18.5,"UNDERWEIGHT",IF(B54<25,"NORMAL WEIGHT",IF(B54<29.9,"OVERWEIGHT","OBESITY"))) -> OBESITY
A55: Id54 | B55: 51.93 | C55: 11.05 | D55: No | E55: No | F55: No | G55: No major surgery | H55: Yes | I55: =IF(H55="?",$H$2,H55) -> Yes | J55: =IF(G55="No major surgery",0,G55) -> 0 | K55: =IF(B55<18.5,"UNDERWEIGHT",IF(B55<25,"NORMAL WEIGHT",IF(B55<29.9,"OVERWEIGHT","OBESITY"))) -> OBESITY
A56: Id55 | B56: 38.95 | C56: 11.95 | D56: No | E56: No | F56: No | G56: No major surgery | H56: Yes | I56: =IF(H56="?",$H$2,H56) -> Yes | J56: =IF(G56="No major surgery",0,G56) -> 0 | K56: =IF(B56<18.5,"UNDERWEIGHT",IF(B56<25,"NORMAL WEIGHT",IF(B56<29.9,"OVERWEIGHT","OBESITY"))) -> OBESITY
A57: Id56 | B57: 36.63 | C57: 7.72 | D57: Yes | E57: No | F57: No | G57: 1 | H57: Yes | I57: =IF(H57="?",$H$2,H57) -> Yes | J57: =IF(G57="No major surgery",0,G57) -> 1 | K57: =IF(B57<18.5,"UNDERWEIGHT",IF(B57<25,"NORMAL WEIGHT",IF(B57<29.9,"OVERWEIGHT","OBESITY"))) -> OBESITY
A58: Id57 | B58: 34.2 | C58: 5.75 | D58: No | E58: No | F58: No | G58: 2 | H58: Yes | I58: =IF(H58="?",$H$2,H58) -> Yes | J58: =IF(G58="No major surgery",0,G58) -> 2 | K58: =IF(B58<18.5,"UNDERWEIGHT",IF(B58<25,"NORMAL WEIGHT",IF(B58<29.9,"OVERWEIGHT","OBESITY"))) -> OBESITY
A59: Id58 | B59: 50.63 | C59: 11.89 | D59: No | E59: No | F59: No | G59: No major surgery | H59: Yes | I59: =IF(H59="?",$H$2,H59) -> Yes | J59: =IF(G59="No major surgery",0,G59) -> 0 | K59: =IF(B59<18.5,"UNDERWEIGHT",IF(B59<25,"NORMAL WEIGHT",IF(B59<29.9,"OVERWEIGHT","OBESITY"))) -> OBESITY
A60: Id59 | B60: 36.48 | C60: 6.2 | D60: No | E60: No | F60: No | G60: No major surgery | H60: Yes | I60: =IF(H60="?",$H$2,H60) -> Yes | J60: =IF(G60="No major surgery",0,G60) -> 0 | K60: =IF(B60<18.5,"UNDERWEIGHT",IF(B60<25,"NORMAL WEIGHT",IF(B60<29.9,"OVERWEIGHT","OBESITY"))) -> OBESITY
A61: Id60 | B61: 54.82 | C61: 10.61 | D61: No | E61: No | F61: No | G61: No major surgery | H61: Yes | I61: =IF(H61="?",$H$2,H61) -> Yes | J61: =IF(G61="No major surgery",0,G61) -> 0 | K61: =IF(B61<18.5,"UNDERWEIGHT",IF(B61<25,"NORMAL WEIGHT",IF(B61<29.9,"OVERWEIGHT","OBESITY"))) -> OBESITY
A62: Id61 | B62: 38.06 | C62: 6.04 | D62: No | E62: No | F62: Yes | G62: 1 | H62: Yes | I62: =IF(H62="?",$H$2,H62) -> Yes | J62: =IF(G62="No major surgery",0,G62) -> 1 | K62: =IF(B62<18.5,"UNDERWEIGHT",IF(B62<25,"NORMAL WEIGHT",IF(B62<29.9,"OVERWEIGHT","OBESITY"))) -> OBESITY
A63: Id62 | B63: 51.48 | C63: 9.33 | D63: Yes | E63: No | F63: No | G63: No major surgery | H63: Yes | I63: =IF(H63="?",$H$2,H63) -> Yes | J63: =IF(G63="No major surgery",0,G63) -> 0 | K63: =IF(B63<18.5,"UNDERWEIGHT",IF(B63<25,"NORMAL WEIGHT",IF(B63<29.9,"OVERWEIGHT","OBESITY"))) -> OBESITY
A64: Id63 | B64: 52.06 | C64: 11.47 | D64: No | E64: No | F64: No | G64: No major surgery | H64: Yes | I64: =IF(H64="?",$H$2,H64) -> Yes | J64: =IF(G64="No major surgery",0,G64) -> 0 | K64: =IF(B64<18.5,"UNDERWEIGHT",IF(B64<25,"NORMAL WEIGHT",IF(B64<29.9,"OVERWEIGHT","OBESITY"))) -> OBESITY
A65: Id64 | B65: 30.685 | C65: 7.02 | D65: Yes | E65: No | F65: No | G65: No major surgery | H65: Yes | I65: =IF(H65="?",$H$2,H65) -> Yes | J65: =IF(G65="No major surgery",0,G65) -> 0 | K65: =IF(B65<18.5,"UNDERWEIGHT",IF(B65<25,"NORMAL WEIGHT",IF(B65<29.9,"OVERWEIGHT","OBESITY"))) -> OBESITY
A66: Id65 | B66: 36.08 | C66: 8.8 | D66: Yes | E66: No | F66: No | G66: 1 | H66: Yes | I66: =IF(H66="?",$H$2,H66) -> Yes | J66: =IF(G66="No major surgery",0,G66) -> 1 | K66: =IF(B66<18.5,"UNDERWEIGHT",IF(B66<25,"NORMAL WEIGHT",IF(B66<29.9,"OVERWEIGHT","OBESITY"))) -> OBESITY
A67: Id66 | B67: 54.99 | C67: 8.68 | D67: No | E67: No | F67: No | G67: 2 | H67: Yes | I67: =IF(H67="?",$H$2,H67) -> Yes | J67: =IF(G67="No major surgery",0,G67) -> 2 | K67: =IF(B67<18.5,"UNDERWEIGHT",IF(B67<25,"NORMAL WEIGHT",IF(B67<29.9,"OVERWEIGHT","OBESITY"))) -> OBESITY
A68: Id67 | B68: 35.97 | C68: 6.12 | D68: No | E68: No | F68: Yes | G68: 1 | H68: Yes | I68: =IF(H68="?",$H$2,H68) -> Yes | J68: =IF(G68="No major surgery",0,G68) -> 1 | K68: =IF(B68<18.5,"UNDERWEIGHT",IF(B68<25,"NORMAL WEIGHT",IF(B68<29.9,"OVERWEIGHT","OBESITY"))) -> OBESITY
A69: Id68 | B69: 45.54 | C69: 5.4 | D69: Yes | E69: No | F69: Yes | G69: 1 | H69: Yes | I69: =IF(H69="?",$H$2,H69) -> Yes | J69: =IF(G69="No major surgery",0,G69) -> 1 | K69: =IF(B69<18.5,"UNDERWEIGHT",IF(B69<25,"NORMAL WEIGHT",IF(B69<29.9,"OVERWEIGHT","OBESITY"))) -> OBESITY
A70: Id69 | B70: 35.53 | C70: 4.36 | D70: Yes | E70: No | F70: No | G70: No major surgery | H70: Yes | I70: =IF(H70="?",$H$2,H70) -> Yes | J70: =IF(G70="No major surgery",0,G70) -> 0 | K70: =IF(B70<18.5,"UNDERWEIGHT",IF(B70<25,"NORMAL WEIGHT",IF(B70<29.9,"OVERWEIGHT","OBESITY"))) -> OBESITY
A71: Id70 | B71: 30.8 | C71: 9.77 | D71: No | E71: No | F71: No | G71: No major surgery | H71: Yes | I71: =IF(H71="?",$H$2,H71) -> Yes | J71: =IF(G71="No major surgery",0,G71) -> 0 | K71: =IF(B71<18.5,"UNDERWEIGHT",IF(B71<25,"NORMAL WEIGHT",IF(B71<29.9,"OVERWEIGHT","OBESITY"))) -> OBESITY
A72: Id71 | B72: 38.39 | C72: 4.25 | D72: No | E72: No | F72: No | G72: 1 | H72: Yes | I72: =IF(H72="?",$H$2,H72) -> Yes | J72: =IF(G72="No major surgery",0,G72) -> 1 | K72: =IF(B72<18.5,"UNDERWEIGHT",IF(B72<25,"NORMAL WEIGHT",IF(B72<29.9,"OVERWEIGHT","OBESITY"))) -> OBESITY
A73: Id72 | B73: 32.3 | C73: 4.76 | D73: No | E73: No | F73: No | G73: 2 | H73: Yes | I73: =IF(H73="?",$H$2,H73) -> Yes | J73: =IF(G73="No major surgery",0,G73) -> 2 | K73: =IF(B73<18.5,"UNDERWEIGHT",IF(B73<25,"NORMAL WEIGHT",IF(B73<29.9,"OVERWEIGHT","OBESITY"))) -> OBESITY
A74: Id73 | B74: 48.8 | C74: 6.22 | D74: Yes | E74: No | F74: No | G74: 2 | H74: Yes | I74: =IF(H74="?",$H$2,H74) -> Yes | J74: =IF(G74="No major surgery",0,G74) -> 2 | K74: =IF(B74<18.5,"UNDERWEIGHT",IF(B74<25,"NORMAL WEIGHT",IF(B74<29.9,"OVERWEIGHT","OBESITY"))) -> OBESITY
A75: Id74 | B75: 45.5 | C75: 7.96 | D75: No | E75: No | F75: No | G75: No major surgery | H75: Yes | I75: =IF(H75="?",$H$2,H75) -> Yes | J75: =IF(G75="No major surgery",0,G75) -> 0 | K75: =IF(B75<18.5,"UNDERWEIGHT",IF(B75<25,"NORMAL WEIGHT",IF(B75<29.9,"OVERWEIGHT","OBESITY"))) -> OBESITY
A76: Id75 | B76: 53.61 | C76: 10.92 | D76: Yes | E76: No | F76: No | G76: 1 | H76: Yes | I76: =IF(H76="?",$H$2,H76) -> Yes | J76: =IF(G76="No major surgery",0,G76) -> 1 | K76: =IF(B76<18.5,"UNDERWEIGHT",IF(B76<25,"NORMAL WEIGHT",IF(B76<29.9,"OVERWEIGHT","OBESITY"))) -> OBESITY
A77: Id76 | B77: 36.19 | C77: 11.51 | D77: Yes | E77: No | F77: No | G77: 1 | H77: Yes | I77: =IF(H77="?",$H$2,H77) -> Yes | J77: =IF(G77="No major surgery",0,G77) -> 1 | K77: =IF(B77<18.5,"UNDERWEIGHT",IF(B77<25,"NORMAL WEIGHT",IF(B77<29.9,"OVERWEIGHT","OBESITY"))) -> OBESITY
A78: Id77 | B78: 34.6 | C78: 5.99 | D78: Yes | E78: No | F78: No | G78: No major surgery | H78: Yes | I78: =IF(H78="?",$H$2,H78) -> Yes | J78: =IF(G78="No major surgery",0,G78) -> 0 | K78: =IF(B78<18.5,"UNDERWEIGHT",IF(B78<25,"NORMAL WEIGHT",IF(B78<29.9,"OVERWEIGHT","OBESITY"))) -> OBESITY
A79: Id78 | B79: 54.12 | C79: 11.57 | D79: No | E79: No | F79: No | G79: No major surgery | H79: Yes | I79: =IF(H79="?",$H$2,H79) -> Yes | J79: =IF(G79="No major surgery",0,G79) -> 0 | K79: =IF(B79<18.5,"UNDERWEIGHT",IF(B79<25,"NORMAL WEIGHT",IF(B79<29.9,"OVERWEIGHT","OBESITY"))) -> OBESITY
A80: Id79 | B80: 48.82 | C80: 6.67 | D80: Yes | E80: No | F80: No | G80: No major surgery | H80: Yes | I80: =IF(H80="?",$H$2,H80) -> Yes | J80: =IF(G80="No major surgery",0,G80) -> 0 | K80: =IF(B80<18.5,"UNDERWEIGHT",IF(B80<25,"NORMAL WEIGHT",IF(B80<29.9,"OVERWEIGHT","OBESITY"))) -> OBESITY
A81: Id80 | B81: 51.01 | C81: 9.2 | D81: No | E81: No | F81: No | G81: No major surgery | H81: Yes | I81: =IF(H81="?",$H$2,H81) -> Yes | J81: =IF(G81="No major surgery",0,G81) -> 0 | K81: =IF(B81<18.5,"UNDERWEIGHT",IF(B81<25,"NORMAL WEIGHT",IF(B81<29.9,"OVERWEIGHT","OBESITY"))) -> OBESITY
A82: Id81 | B82: 45.65 | C82: 5.11 | D82: Yes | E82: No | F82: No | G82: 1 | H82: Yes | I82: =IF(H82="?",$H$2,H82) -> Yes | J82: =IF(G82="No major surgery",0,G82) -> 1 | K82: =IF(B82<18.5,"UNDERWEIGHT",IF(B82<25,"NORMAL WEIGHT",IF(B82<29.9,"OVERWEIGHT","OBESITY"))) -> OBESITY
A83: Id82 | B83: 52.9 | C83: 5.34 | D83: No | E83: No | F83: No | G83: No major surgery | H83: Yes | I83: =IF(H83="?",$H$2,H83) -> Yes | J83: =IF(G83="No major surgery",0,G83) -> 0 | K83: =IF(B83<18.5,"UNDERWEIGHT",IF(B83<25,"NORMAL WEIGHT",IF(B83<29.9,"OVERWEIGHT","OBESITY"))) -> OBESITY
A84: Id83 | B84: 45.41 | C84: 4.03 | D84: Yes | E84: No | F84: No | G84: 1 | H84: Yes | I84: =IF(H84="?",$H$2,H84) -> Yes | J84: =IF(G84="No major surgery",0,G84) -> 1 | K84: =IF(B84<18.5,"UNDERWEIGHT",IF(B84<25,"NORMAL WEIGHT",IF(B84<29.9,"OVERWEIGHT","OBESITY"))) -> OBESITY
A85: Id84 | B85: 49.41 | C85: 4.23 | D85: Yes | E85: No | F85: Yes | G85: 1 | H85: Yes | I85: =IF(H85="?",$H$2,H85) -> Yes | J85: =IF(G85="No major surgery",0,G85) -> 1 | K85: =IF(B85<18.5,"UNDERWEIGHT",IF(B85<25,"NORMAL WEIGHT",IF(B85<29.9,"OVERWEIGHT","OBESITY"))) -> OBESITY
A86: Id85 | B86: 31.825 | C86: 4.06 | D86: No | E86: No | F86: No | G86: 2 | H86: Yes | I86: =IF(H86="?",$H$2,H86) -> Yes | J86: =IF(G86="No major surgery",0,G86) -> 2 | K86: =IF(B86<18.5,"UNDERWEIGHT",IF(B86<25,"NORMAL WEIGHT",IF(B86<29.9,"OVERWEIGHT","OBESITY"))) -> OBESITY
A87: Id86 | B87: 51.28 | C87: 4.68 | D87: No | E87: No | F87: No | G87: 2 | H87: Yes | I87: =IF(H87="?",$H$2,H87) -> Yes | J87: =IF(G87="No major surgery",0,G87) -> 2 | K87: =IF(B87<18.5,"UNDERWEIGHT",IF(B87<25,"NORMAL WEIGHT",IF(B87<29.9,"OVERWEIGHT","OBESITY"))) -> OBESITY
A88: Id87 | B88: 34.96 | C88: 4.34 | D88: No | E88: No | F88: Yes | G88: 1 | H88: Yes | I88: =IF(H88="?",$H$2,H88) -> Yes | J88: =IF(G88="No major surgery",0,G88) -> 1 | K88: =IF(B88<18.5,"UNDERWEIGHT",IF(B88<25,"NORMAL WEIGHT",IF(B88<29.9,"OVERWEIGHT","OBESITY"))) -> OBESITY
A89: Id88 | B89: 33.11 | C89: 10.51 | D89: No | E89: No | F89: No | G89: No major surgery | H89: Yes | I89: =IF(H89="?",$H$2,H89) -> Yes | J89: =IF(G89="No major surgery",0,G89) -> 0 | K89: =IF(B89<18.5,"UNDERWEIGHT",IF(B89<25,"NORMAL WEIGHT",IF(B89<29.9,"OVERWEIGHT","OBESITY"))) -> OBESITY
A90: Id89 | B90: 54.74 | C90: 5.84 | D90: Yes | E90: No | F90: Yes | G90: 1 | H90: Yes | I90: =IF(H90="?",$H$2,H90) -> Yes | J90: =IF(G90="No major surgery",0,G90) -> 1 | K90: =IF(B90<18.5,"UNDERWEIGHT",IF(B90<25,"NORMAL WEIGHT",IF(B90<29.9,"OVERWEIGHT","OBESITY"))) -> OBESITY
A91: Id90 | B91: 32.56 | C91: 5.41 | D91: No | E91: No | F91: Yes | G91: 1 | H91: Yes | I91: =IF(H91="?",$H$2,H91) -> Yes | J91: =IF(G91="No major surgery",0,G91) -> 1 | K91: =IF(B91<18.5,"UNDERWEIGHT",IF(B91<25,"NORMAL WEIGHT",IF(B91<29.9,"OVERWEIGHT","OBESITY"))) -> OBESITY
A92: Id91 | B92: 39.05 | C92: 6.06 | D92: No | E92: No | F92: No | G92: 1 | H92: Yes | I92: =IF(H92="?",$H$2,H92) -> Yes | J92: =IF(G92="No major surgery",0,G92) -> 1 | K92: =IF(B92<18.5,"UNDERWEIGHT",IF(B92<25,"NORMAL WEIGHT",IF(B92<29.9,"OVERWEIGHT","OBESITY"))) -> OBESITY
A93: Id92 | B93: 42.75 | C93: 4.22 | D93: No | E93: No | F93: No | G93: No major surgery | H93: Yes | I93: =IF(H93="?",$H$2,H93) -> Yes | J93: =IF(G93="No major surgery",0,G93) -> 0 | K93: =IF(B93<18.5,"UNDERWEIGHT",IF(B93<25,"NORMAL WEIGHT",IF(B93<29.9,"OVERWEIGHT","OBESITY"))) -> OBESITY
A94: Id93 | B94: 50.58 | C94: 5.12 | D94: No | E94: No | F94: No | G94: 2 | H94: Yes | I94: =IF(H94="?",$H$2,H94) -> Yes | J94: =IF(G94="No major surgery",0,G94) -> 2 | K94: =IF(B94<18.5,"UNDERWEIGHT",IF(B94<25,"NORMAL WEIGHT",IF(B94<29.9,"OVERWEIGHT","OBESITY"))) -> OBESITY
A95: Id94 | B95: 30.495 | C95: 4.57 | D95: Yes | E95: No | F95: No | G95: No major surgery | H95: Yes | I95: =IF(H95="?",$H$2,H95) -> Yes | J95: =IF(G95="No major surgery",0,G95) -> 0 | K95: =IF(B95<18.5,"UNDERWEIGHT",IF(B95<25,"NORMAL WEIGHT",IF(B95<29.9,"OVERWEIGHT","OBESITY"))) -> OBESITY
A96: Id95 | B96: 48.31 | C96: 9.58 | D96: Yes | E96: No | F96: No | G96: 2 | H96: Yes | I96: =IF(H96="?",$H$2,H96) -> Yes | J96: =IF(G96="No major surgery",0,G96) -> 2 | K96: =IF(B96<18.5,"UNDERWEIGHT",IF(B96<25,"NORMAL WEIGHT",IF(B96<29.9,"OVERWEIGHT","OBESITY"))) -> OBESITY
A97: Id96 | B97: 48.99 | C97: 9.78 | D97: Yes | E97: No | F97: No | G97: 1 | H97: Yes | I97: =IF(H97="?",$H$2,H97) -> Yes | J97: =IF(G97="No major surgery",0,G97) -> 1 | K97: =IF(B97<18.5,"UNDERWEIGHT",IF(B97<25,"NORMAL WEIGHT",IF(B97<29.9,"OVERWEIGHT","OBESITY"))) -> OBESITY
A98: Id97 | B98: 38.39 | C98: 4.11 | D98: Yes | E98: No | F98: No | G98: No major surgery | H98: Yes | I98: =IF(H98="?",$H$2,H98) -> Yes | J98: =IF(G98="No major surgery",0,G98) -> 0 | K98: =IF(B98<18.5,"UNDERWEIGHT",IF(B98<25,"NORMAL WEIGHT",IF(B98<29.9,"OVERWEIGHT","OBESITY"))) -> OBESITY
A99: Id98 | B99: 44.34 | C99: 4.02 | D99: Yes | E99: No | F99: No | G99: 2 | H99: Yes | I99: =IF(H99="?",$H$2,H99) -> Yes | J99: =IF(G99="No major surgery",0,G99) -> 2 | K99: =IF(B99<18.5,"UNDERWEIGHT",IF(B99<25,"NORMAL WEIGHT",IF(B99<29.9,"OVERWEIGHT","OBESITY"))) -> OBESITY
A100: Id99 | B100: 41.51 | C100: 6.92 | D100: No | E100: No | F100: No | G100: No major surgery | H100: Yes | I100: =IF(H100="?",$H$2,H100) -> Yes | J100: =IF(G100="No major surgery",0,G100) -> 0 | K100: =IF(B100<18.5,"UNDERWEIGHT",IF(B100<25,"NORMAL WEIGHT",IF(B100<29.9,"OVERWEIGHT","OBESITY"))) -> OBESITY
...

Sheet Hospitalisation Details
A1: Customer ID | B1: Year | C1: MONTH | D1: Date | E1: DATE OF BIRTH | F1: Children | G1: Charges | H1: Hospital tier | I1: City tier | J1: State ID | K1: AVERAGE YEAR | L1: HOSPITAL TIER | M1: CITY TIER | N1: STATE ID | O1: Age | P1: DATE OF BIRTH
A2: Id999 | B2: 1969 | C2: Aug | D2: 20 | E2: =DATE(K2, MONTH(1 & C2), D2) -> 25435 | F2: 3 | G2: 11253.42 | H2: tier - 3 | I2: tier - 1 | J2: R1011 | K2: =IF(B2="?",ROUND(AVERAGE($B$2:$B$2344),0),B2) -> 1969 | L2: =IF(H2="?",$H$2,H2) -> tier - 3 | M2: =IF(I2="?",$I$2,I2) -> tier - 1 | N2: =IF(J2="?","UNKNOWN",J2) -> R1011 | O2: =IFERROR(INT(YEARFRAC(E2, DATE(2023,6,8))), "") -> 53 | P2: 25435 | R2: =Q28-B2 -> 43116
A3: Id998 | B3: 1981 | C3: Oct | D3: 2 | E3: =DATE(K3, MONTH(1 & C3), D3) -> 29861 | F3: 1 | G3: 11255.29 | H3: tier - 3 | I3: tier - 1 | J3: R1026 | K3: =IF(B3="?",ROUND(AVERAGE($B$2:$B$2344),0),B3) -> 1981 | L3: =IF(H3="?",$H$2,H3) -> tier - 3 | M3: =IF(I3="?",$I$2,I3) -> tier - 1 | N3: =IF(J3="?","UNKNOWN",J3) -> R1026 | O3: =IFERROR(INT(YEARFRAC(E3, DATE(2023,6,8))), "") -> 41 | P3: 29861 | Q3: NO. OF "?' IN CUSTOMER COLUMN | R3: COUNTIF | S3: =COUNTIF(A2:A2344,"?") -> 6
A4: Id997 | B4: 1969 | C4: Oct | D4: 11 | E4: =DATE(K4, MONTH(1 & C4), D4) -> 25487 | F4: 3 | G4: 11264.54 | H4: tier - 3 | I4: tier - 2 | J4: R1011 | K4: =IF(B4="?",ROUND(AVERAGE($B$2:$B$2344),0),B4) -> 1969 | L4: =IF(H4="?",$H$2,H4) -> tier - 3 | M4: =IF(I4="?",$I$2,I4) -> tier - 2 | N4: =IF(J4="?","UNKNOWN",J4) -> R1011 | O4: =IFERROR(INT(YEARFRAC(E4, DATE(2023,6,8))), "") -> 53 | P4: 25487 | Q4: NO.OF "?" IN YEAR COLUMN | R4: COUNTIF | S4: =COUNTIF(B2:B2344,"?") -> 2
A5: Id996 | B5: 1971 | C5: Dec | D5: 26 | E5: =DATE(K5, MONTH(1 & C5), D5) -> 26293 | F5: 0 | G5: 11265.71 | H5: tier - 3 | I5: tier - 1 | J5: R1025 | K5: =IF(B5="?",ROUND(AVERAGE($B$2:$B$2344),0),B5) -> 1971 | L5: =IF(H5="?",$H$2,H5) -> tier - 3 | M5: =IF(I5="?",$I$2,I5) -> tier - 1 | N5: =IF(J5="?","UNKNOWN",J5) -> R1025 | O5: =IFERROR(INT(YEARFRAC(E5, DATE(2023,6,8))), "") -> 51 | P5: 26293 | Q5: NO.OF "?" IN MONTH COLUMN | R5: COUNTIF | S5: =COUNTIF(C2:C2344,"?") -> 0
A6: Id995 | B6: 2004 | C6: Oct | D6: 4 | E6: =DATE(K6, MONTH(1 & C6), D6) -> 38264 | F6: 1 | G6: 11272.33 | H6: tier - 3 | I6: tier - 2 | J6: R1019 | K6: =IF(B6="?",ROUND(AVERAGE($B$2:$B$2344),0),B6) -> 2004 | L6: =IF(H6="?",$H$2,H6) -> tier - 3 | M6: =IF(I6="?",$I$2,I6) -> tier - 2 | N6: =IF(J6="?","UNKNOWN",J6) -> R1019 | O6: =IFERROR(INT(YEARFRAC(E6, DATE(2023,6,8))), "") -> 18 | P6: 38264 | Q6: NO.OF "?" IN DATE COLUMN | R6: COUNTIF | S6: =COUNTIF(D2:D2344,"?") -> 0
A7: Id994 | B7: 1967 | C7: Jun | D7: 14 | E7: =DATE(K7, MONTH(1 & C7), D7) -> 24637 | F7: 0 | G7: 11286.54 | H7: tier - 3 | I7: tier - 3 | J7: R1024 | K7: =IF(B7="?",ROUND(AVERAGE($B$2:$B$2344),0),B7) -> 1967 | L7: =IF(H7="?",$H$2,H7) -> tier - 3 | M7: =IF(I7="?",$I$2,I7) -> tier - 3 | N7: =IF(J7="?","UNKNOWN",J7) -> R1024 | O7: =IFERROR(INT(YEARFRAC(E7, DATE(2023,6,8))), "") -> 55 | P7: 24637 | Q7: NO.OF "?" IN CHILDREN COLUMN | R7: COUNTIF | S7: =COUNTIF(F2:F2344,"?") -> 0
A8: Id993 | B8: 1970 | C8: Jun | D8: 22 | E8: =DATE(K8, MONTH(1 & C8), D8) -> 25741 | F8: 3 | G8: 11289.11 | H8: tier - 3 | I8: tier - 1 | J8: R1012 | K8: =IF(B8="?",ROUND(AVERAGE($B$2:$B$2344),0),B8) -> 1970 | L8: =IF(H8="?",$H$2,H8) -> tier - 3 | M8: =IF(I8="?",$I$2,I8) -> tier - 1 | N8: =IF(J8="?","UNKNOWN",J8) -> R1012 | O8: =IFERROR(INT(YEARFRAC(E8, DATE(2023,6,8))), "") -> 52 | P8: 25741 | Q8: NO.OF "?" IN CHARGES COLUMN | R8: COUNTIF | S8: =COUNTIF(G2:G2344,"?") -> 0
A9: Id992 | B9: 1988 | C9: Nov | D9: 14 | E9: =DATE(K9, MONTH(1 & C9), D9) -> 32461 | F9: 3 | G9: 11294.57 | H9: tier - 3 | I9: tier - 1 | J9: R1022 | K9: =IF(B9="?",ROUND(AVERAGE($B$2:$B$2344),0),B9) -> 1988 | L9: =IF(H9="?",$H$2,H9) -> tier - 3 | M9: =IF(I9="?",$I$2,I9) -> tier - 1 | N9: =IF(J9="?","UNKNOWN",J9) -> R1022 | O9: =IFERROR(INT(YEARFRAC(E9, DATE(2023,6,8))), "") -> 34 | P9: 32461 | Q9: NO.OF "?" IN HOSPITAL TIER COLUMN | R9: COUNTIF | S9: =COUNTIF(H2:H2344,"?") -> 1
A10: Id991 | B10: 1972 | C10: Sep | D10: 25 | E10: =DATE(K10, MONTH(1 & C10), D10) -> 26567 | F10: 4 | G10: 11299.34 | H10: tier - 3 | I10: tier - 2 | J10: R1011 | K10: =IF(B10="?",ROUND(AVERAGE($B$2:$B$2344),0),B10) -> 1972 | L10: =IF(H10="?",$H$2,H10) -> tier - 3 | M10: =IF(I10="?",$I$2,I10) -> tier - 2 | N10: =IF(J10="?","UNKNOWN",J10) -> R1011 | O10: =IFERROR(INT(YEARFRAC(E10, DATE(2023,6,8))), "") -> 50 | P10: 26567 | Q10: NO.OF "?" IN CITY TIERCOLUMN | R10: COUNTIF | S10: =COUNTIF(I2:I2344,"?") -> 1
A11: Id990 | B11: 1968 | C11: Oct | D11: 6 | E11: =DATE(K11, MONTH(1 & C11), D11) -> 25117 | F11: 1 | G11: 11305.93 | H11: tier - 3 | I11: tier - 1 | J11: R1012 | K11: =IF(B11="?",ROUND(AVERAGE($B$2:$B$2344),0),B11) -> 1968 | L11: =IF(H11="?",$H$2,H11) -> tier - 3 | M11: =IF(I11="?",$I$2,I11) -> tier - 1 | N11: =IF(J11="?","UNKNOWN",J11) -> R1012 | O11: =IFERROR(INT(YEARFRAC(E11, DATE(2023,6,8))), "") -> 54 | P11: 25117 | Q11: NO.OF "?" IN STATE COLUMN | R11: COUNTIF | S11: =COUNTIF(J2:J2344,"?") -> 2
A12: Id99 | B12: 1962 | C12: Sep | D12: 4 | E12: =DATE(K12, MONTH(1 & C12), D12) -> 22893 | F12: 0 | G12: 40309.93 | H12: tier - 1 | I12: tier - 3 | J12: R1011 | K12: =IF(B12="?",ROUND(AVERAGE($B$2:$B$2344),0),B12) -> 1962 | L12: =IF(H12="?",$H$2,H12) -> tier - 1 | M12: =IF(I12="?",$I$2,I12) -> tier - 3 | N12: =IF(J12="?","UNKNOWN",J12) -> R1011 | O12: =IFERROR(INT(YEARFRAC(E12, DATE(2023,6,8))), "") -> 60 | P12: 22893 | R12: TOTAL | S12: =SUM(S3:S11) -> 12
A13: Id989 | B13: 1963 | C13: Nov | D13: 22 | E13: =DATE(K13, MONTH(1 & C13), D13) -> 23337 | F13: 0 | G13: 11312.33 | H13: tier - 3 | I13: tier - 3 | J13: R1012 | K13: =IF(B13="?",ROUND(AVERAGE($B$2:$B$2344),0),B13) -> 1963 | L13: =IF(H13="?",$H$2,H13) -> tier - 3 | M13: =IF(I13="?",$I$2,I13) -> tier - 3 | N13: =IF(J13="?","UNKNOWN",J13) -> R1012 | O13: =IFERROR(INT(YEARFRAC(E13, DATE(2023,6,8))), "") -> 59 | P13: 23337
A14: Id988 | B14: 1995 | C14: Dec | D14: 10 | E14: =DATE(K14, MONTH(1 & C14), D14) -> 35043 | F14: 0 | G14: 11318.57 | H14: tier - 3 | I14: tier - 2 | J14: R1026 | K14: =IF(B14="?",ROUND(AVERAGE($B$2:$B$2344),0),B14) -> 1995 | L14: =IF(H14="?",$H$2,H14) -> tier - 3 | M14: =IF(I14="?",$I$2,I14) -> tier - 2 | N14: =IF(J14="?","UNKNOWN",J14) -> R1026 | O14: =IFERROR(INT(YEARFRAC(E14, DATE(2023,6,8))), "") -> 27 | P14: 35043
A15: Id987 | B15: 1963 | C15: Jul | D15: 11 | E15: =DATE(K15, MONTH(1 & C15), D15) -> 23203 | F15: 0 | G15: 11319.12 | H15: tier - 3 | I15: tier - 1 | J15: R1012 | K15: =IF(B15="?",ROUND(AVERAGE($B$2:$B$2344),0),B15) -> 1963 | L15: =IF(H15="?",$H$2,H15) -> tier - 3 | M15: =IF(I15="?",$I$2,I15) -> tier - 1 | N15: =IF(J15="?","UNKNOWN",J15) -> R1012 | O15: =IFERROR(INT(YEARFRAC(E15, DATE(2023,6,8))), "") -> 59 | P15: 23203
A16: Id986 | B16: 2002 | C16: Sep | D16: 20 | E16: =DATE(K16, MONTH(1 & C16), D16) -> 37519 | F16: 0 | G16: 11321.49 | H16: tier - 3 | I16: tier - 3 | J16: R1012 | K16: =IF(B16="?",ROUND(AVERAGE($B$2:$B$2344),0),B16) -> 2002 | L16: =IF(H16="?",$H$2,H16) -> tier - 3 | M16: =IF(I16="?",$I$2,I16) -> tier - 3 | N16: =IF(J16="?","UNKNOWN",J16) -> R1012 | O16: =IFERROR(INT(YEARFRAC(E16, DATE(2023,6,8))), "") -> 20 | P16: 37519 | Q16: HOSPITAL REPEATED TIER - 1 | R16: COUNTIF | S16: =COUNTIF(L2:L2344,"tier - 1") -> 309
A17: Id985 | B17: 1989 | C17: Aug | D17: 19 | E17: =DATE(K17, MONTH(1 & C17), D17) -> 32739 | F17: 1 | G17: 11326.71 | H17: tier - 3 | I17: tier - 3 | J17: R1013 | K17: =IF(B17="?",ROUND(AVERAGE($B$2:$B$2344),0),B17) -> 1989 | L17: =IF(H17="?",$H$2,H17) -> tier - 3 | M17: =IF(I17="?",$I$2,I17) -> tier - 3 | N17: =IF(J17="?","UNKNOWN",J17) -> R1013 | O17: =IFERROR(INT(YEARFRAC(E17, DATE(2023,6,8))), "") -> 33 | P17: 32739 | Q17: HOSPITAL REPEATED TIER - 2 | R17: COUNTIF | S17: =COUNTIF(L2:L2344,"tier - 2") -> 1339
A18: Id984 | B18: 1968 | C18: Nov | D18: 2 | E18: =DATE(K18, MONTH(1 & C18), D18) -> 25144 | F18: 0 | G18: 11344.32 | H18: tier - 3 | I18: tier - 2 | J18: R1025 | K18: =IF(B18="?",ROUND(AVERAGE($B$2:$B$2344),0),B18) -> 1968 | L18: =IF(H18="?",$H$2,H18) -> tier - 3 | M18: =IF(I18="?",$I$2,I18) -> tier - 2 | N18: =IF(J18="?","UNKNOWN",J18) -> R1025 | O18: =IFERROR(INT(YEARFRAC(E18, DATE(2023,6,8))), "") -> 54 | P18: 25144 | Q18: HOSPITAL REPEATED TIER - 3 | R18: COUNTIF | S18: =COUNTIF(L2:L2344,"tier - 3") -> 695
A19: Id983 | B19: 1964 | C19: Jul | D19: 12 | E19: =DATE(K19, MONTH(1 & C19), D19) -> 23570 | F19: 0 | G19: 11345.52 | H19: tier - 3 | I19: tier - 3 | J19: R1011 | K19: =IF(B19="?",ROUND(AVERAGE($B$2:$B$2344),0),B19) -> 1964 | L19: =IF(H19="?",$H$2,H19) -> tier - 3 | M19: =IF(I19="?",$I$2,I19) -> tier - 3 | N19: =IF(J19="?","UNKNOWN",J19) -> R1011 | O19: =IFERROR(INT(YEARFRAC(E19, DATE(2023,6,8))), "") -> 58 | P19: 23570
A20: Id982 | B20: 1965 | C20: Nov | D20: 29 | E20: =DATE(K20, MONTH(1 & C20), D20) -> 24075 | F20: 0 | G20: 11353.23 | H20: tier - 3 | I20: tier - 1 | J20: R1012 | K20: =IF(B20="?",ROUND(AVERAGE($B$2:$B$2344),0),B20) -> 1965 | L20: =IF(H20="?",$H$2,H20) -> tier - 3 | M20: =IF(I20="?",$I$2,I20) -> tier - 1 | N20: =IF(J20="?","UNKNOWN",J20) -> R1012 | O20: =IFERROR(INT(YEARFRAC(E20, DATE(2023,6,8))), "") -> 57 | P20: 24075
A21: Id981 | B21: 1965 | C21: Sep | D21: 26 | E21: =DATE(K21, MONTH(1 & C21), D21) -> 24011 | F21: 0 | G21: 11356.66 | H21: tier - 3 | I21: tier - 3 | J21: R1012 | K21: =IF(B21="?",ROUND(AVERAGE($B$2:$B$2344),0),B21) -> 1965 | L21: =IF(H21="?",$H$2,H21) -> tier - 3 | M21: =IF(I21="?",$I$2,I21) -> tier - 3 | N21: =IF(J21="?","UNKNOWN",J21) -> R1012 | O21: =IFERROR(INT(YEARFRAC(E21, DATE(2023,6,8))), "") -> 57 | P21: 24011 | Q21: CITY TIER - 1 | R21: COUNTIF | S21: =COUNTIF(M2:M2344,"tier - 1") -> 735
A22: Id980 | B22: 1964 | C22: Jul | D22: 4 | E22: =DATE(K22, MONTH(1 & C22), D22) -> 23562 | F22: 0 | G22: 11362.76 | H22: tier - 3 | I22: tier - 1 | J22: R1011 | K22: =IF(B22="?",ROUND(AVERAGE($B$2:$B$2344),0),B22) -> 1964 | L22: =IF(H22="?",$H$2,H22) -> tier - 3 | M22: =IF(I22="?",$I$2,I22) -> tier - 1 | N22: =IF(J22="?","UNKNOWN",J22) -> R1011 | O22: =IFERROR(INT(YEARFRAC(E22, DATE(2023,6,8))), "") -> 58 | P22: 23562 | Q22: CITY TIER - 2 | R22: COUNTIF | S22: =COUNTIF(M2:M2344,"tier - 2") -> 812
A23: Id98 | B23: 1966 | C23: Aug | D23: 12 | E23: =DATE(K23, MONTH(1 & C23), D23) -> 24331 | F23: 0 | G23: 40373.74 | H23: tier - 1 | I23: tier - 3 | J23: R1011 | K23: =IF(B23="?",ROUND(AVERAGE($B$2:$B$2344),0),B23) -> 1966 | L23: =IF(H23="?",$H$2,H23) -> tier - 1 | M23: =IF(I23="?",$I$2,I23) -> tier - 3 | N23: =IF(J23="?","UNKNOWN",J23) -> R1011 | O23: =IFERROR(INT(YEARFRAC(E23, DATE(2023,6,8))), "") -> 56 | P23: 24331 | Q23: CITY TIER - 3 | R23: COUNTIF | S23: =COUNTIF(M2:M2344,"tier - 3") -> 796
A24: Id979 | B24: 1964 | C24: Jul | D24: 3 | E24: =DATE(K24, MONTH(1 & C24), D24) -> 23561 | F24: 0 | G24: 11363.28 | H24: tier - 3 | I24: tier - 1 | J24: R1013 | K24: =IF(B24="?",ROUND(AVERAGE($B$2:$B$2344),0),B24) -> 1964 | L24: =IF(H24="?",$H$2,H24) -> tier - 3 | M24: =IF(I24="?",$I$2,I24) -> tier - 1 | N24: =IF(J24="?","UNKNOWN",J24) -> R1013 | O24: =IFERROR(INT(YEARFRAC(E24, DATE(2023,6,8))), "") -> 58 | P24: 23561
A25: Id978 | B25: 1964 | C25: Dec | D25: 13 | E25: =DATE(K25, MONTH(1 & C25), D25) -> 23724 | F25: 0 | G25: 11365.95 | H25: tier - 3 | I25: tier - 2 | J25: R1011 | K25: =IF(B25="?",ROUND(AVERAGE($B$2:$B$2344),0),B25) -> 1964 | L25: =IF(H25="?",$H$2,H25) -> tier - 3 | M25: =IF(I25="?",$I$2,I25) -> tier - 2 | N25: =IF(J25="?","UNKNOWN",J25) -> R1011 | O25: =IFERROR(INT(YEARFRAC(E25, DATE(2023,6,8))), "") -> 58 | P25: 23724 | R25: DATE OF COLLECTION
A26: Id977 | B26: 1979 | C26: Jun | D26: 7 | E26: =DATE(K26, MONTH(1 & C26), D26) -> 29013 | F26: 2 | G26: 11369.39 | H26: tier - 3 | I26: tier - 1 | J26: R1026 | K26: =IF(B26="?",ROUND(AVERAGE($B$2:$B$2344),0),B26) -> 1979 | L26: =IF(H26="?",$H$2,H26) -> tier - 3 | M26: =IF(I26="?",$I$2,I26) -> tier - 1 | N26: =IF(J26="?","UNKNOWN",J26) -> R1026 | O26: =IFERROR(INT(YEARFRAC(E26, DATE(2023,6,8))), "") -> 44 | P26: 29013
A27: Id976 | B27: 1972 | C27: Dec | D27: 6 | E27: =DATE(K27, MONTH(1 & C27), D27) -> 26639 | F27: 0 | G27: 11378.57 | H27: tier - 3 | I27: tier - 2 | J27: R1025 | K27: =IF(B27="?",ROUND(AVERAGE($B$2:$B$2344),0),B27) -> 1972 | L27: =IF(H27="?",$H$2,H27) -> tier - 3 | M27: =IF(I27="?",$I$2,I27) -> tier - 2 | N27: =IF(J27="?","UNKNOWN",J27) -> R1025 | O27: =IFERROR(INT(YEARFRAC(E27, DATE(2023,6,8))), "") -> 50 | P27: 26639
A28: Id975 | B28: 1964 | C28: Jun | D28: 13 | E28: =DATE(K28, MONTH(1 & C28), D28) -> 23541 | F28: 0 | G28: 11381.33 | H28: tier - 3 | I28: tier - 2 | J28: R1013 | K28: =IF(B28="?",ROUND(AVERAGE($B$2:$B$2344),0),B28) -> 1964 | L28: =IF(H28="?",$H$2,H28) -> tier - 3 | M28: =IF(I28="?",$I$2,I28) -> tier - 2 | N28: =IF(J28="?","UNKNOWN",J28) -> R1013 | O28: =IFERROR(INT(YEARFRAC(E28, DATE(2023,6,8))), "") -> 58 | P28: 23541 | Q28: 45085
A29: Id974 | B29: 1997 | C29: Jul | D29: 28 | E29: =DATE(K29, MONTH(1 & C29), D29) -> 35639 | F29: 0 | G29: 11388.27 | H29: tier - 3 | I29: tier - 2 | J29: R1026 | K29: =IF(B29="?",ROUND(AVERAGE($B$2:$B$2344),0),B29) -> 1997 | L29: =IF(H29="?",$H$2,H29) -> tier - 3 | M29: =IF(I29="?",$I$2,I29) -> tier - 2 | N29: =IF(J29="?","UNKNOWN",J29) -> R1026 | O29: =IFERROR(INT(YEARFRAC(E29, DATE(2023,6,8))), "") -> 25 | P29: 35639
A30: Id973 | B30: 1967 | C30: Dec | D30: 19 | E30: =DATE(K30, MONTH(1 & C30), D30) -> 24825 | F30: 1 | G30: 11394.07 | H30: tier - 3 | I30: tier - 1 | J30: R1018 | K30: =IF(B30="?",ROUND(AVERAGE($B$2:$B$2344),0),B30) -> 1967 | L30: =IF(H30="?",$H$2,H30) -> tier - 3 | M30: =IF(I30="?",$I$2,I30) -> tier - 1 | N30: =IF(J30="?","UNKNOWN",J30) -> R1018 | O30: =IFERROR(INT(YEARFRAC(E30, DATE(2023,6,8))), "") -> 55 | P30: 24825
A31: Id972 | B31: 1970 | C31: Oct | D31: 2 | E31: =DATE(K31, MONTH(1 & C31), D31) -> 25843 | F31: 2 | G31: 11396.9 | H31: tier - 3 | I31: tier - 3 | J31: R1024 | K31: =IF(B31="?",ROUND(AVERAGE($B$2:$B$2344),0),B31) -> 1970 | L31: =IF(H31="?",$H$2,H31) -> tier - 3 | M31: =IF(I31="?",$I$2,I31) -> tier - 3 | N31: =IF(J31="?","UNKNOWN",J31) -> R1024 | O31: =IFERROR(INT(YEARFRAC(E31, DATE(2023,6,8))), "") -> 52 | P31: 25843
A32: Id971 | B32: 1970 | C32: Oct | D32: 7 | E32: =DATE(K32, MONTH(1 & C32), D32) -> 25848 | F32: 3 | G32: 11411.69 | H32: tier - 3 | I32: tier - 2 | J32: R1011 | K32: =IF(B32="?",ROUND(AVERAGE($B$2:$B$2344),0),B32) -> 1970 | L32: =IF(H32="?",$H$2,H32) -> tier - 3 | M32: =IF(I32="?",$I$2,I32) -> tier - 2 | N32: =IF(J32="?","UNKNOWN",J32) -> R1011 | O32: =IFERROR(INT(YEARFRAC(E32, DATE(2023,6,8))), "") -> 52 | P32: 25848
A33: Id970 | B33: 1983 | C33: Oct | D33: 23 | E33: =DATE(K33, MONTH(1 & C33), D33) -> 30612 | F33: 3 | G33: 11412.02 | H33: tier - 3 | I33: tier - 1 | J33: R1021 | K33: =IF(B33="?",ROUND(AVERAGE($B$2:$B$2344),0),B33) -> 1983 | L33: =IF(H33="?",$H$2,H33) -> tier - 3 | M33: =IF(I33="?",$I$2,I33) -> tier - 1 | N33: =IF(J33="?","UNKNOWN",J33) -> R1021 | O33: =IFERROR(INT(YEARFRAC(E33, DATE(2023,6,8))), "") -> 39 | P33: 30612
A34: Id97 | B34: 1985 | C34: Nov | D34: 3 | E34: =DATE(K34, MONTH(1 & C34), D34) -> 31354 | F34: 0 | G34: 40419.02 | H34: tier - 1 | I34: tier - 2 | J34: R1013 | K34: =IF(B34="?",ROUND(AVERAGE($B$2:$B$2344),0),B34) -> 1985 | L34: =IF(H34="?",$H$2,H34) -> tier - 1 | M34: =IF(I34="?",$I$2,I34) -> tier - 2 | N34: =IF(J34="?","UNKNOWN",J34) -> R1013 | O34: =IFERROR(INT(YEARFRAC(E34, DATE(2023,6,8))), "") -> 37 | P34: 31354
A35: Id969 | B35: 1985 | C35: Jun | D35: 9 | E35: =DATE(K35, MONTH(1 & C35), D35) -> 31207 | F35: 3 | G35: 11419.49 | H35: tier - 3 | I35: tier - 1 | J35: R1012 | K35: =IF(B35="?",ROUND(AVERAGE($B$2:$B$2344),0),B35) -> 1985 | L35: =IF(H35="?",$H$2,H35) -> tier - 3 | M35: =IF(I35="?",$I$2,I35) -> tier - 1 | N35: =IF(J35="?","UNKNOWN",J35) -> R1012 | O35: =IFERROR(INT(YEARFRAC(E35, DATE(2023,6,8))), "") -> 37 | P35: 31207
A36: Id968 | B36: 1980 | C36: Jul | D36: 17 | E36: =DATE(K36, MONTH(1 & C36), D36) -> 29419 | F36: 2 | G36: 11435.74 | H36: tier - 3 | I36: tier - 3 | J36: R1021 | K36: =IF(B36="?",ROUND(AVERAGE($B$2:$B$2344),0),B36) -> 1980 | L36: =IF(H36="?",$H$2,H36) -> tier - 3 | M36: =IF(I36="?",$I$2,I36) -> tier - 3 | N36: =IF(J36="?","UNKNOWN",J36) -> R1021 | O36: =IFERROR(INT(YEARFRAC(E36, DATE(2023,6,8))), "") -> 42 | P36: 29419
A37: Id967 | B37: 1971 | C37: Sep | D37: 12 | E37: =DATE(K37, MONTH(1 & C37), D37) -> 26188 | F37: 3 | G37: 11436.74 | H37: tier - 3 | I37: tier - 3 | J37: R1012 | K37: =IF(B37="?",ROUND(AVERAGE($B$2:$B$2344),0),B37) -> 1971 | L37: =IF(H37="?",$H$2,H37) -> tier - 3 | M37: =IF(I37="?",$I$2,I37) -> tier - 3 | N37: =IF(J37="?","UNKNOWN",J37) -> R1012 | O37: =IFERROR(INT(YEARFRAC(E37, DATE(2023,6,8))), "") -> 51 | P37: 26188
A38: Id966 | B38: 1966 | C38: Jun | D38: 14 | E38: =DATE(K38, MONTH(1 & C38), D38) -> 24272 | F38: 0 | G38: 11454.02 | H38: tier - 3 | I38: tier - 1 | J38: R1012 | K38: =IF(B38="?",ROUND(AVERAGE($B$2:$B$2344),0),B38) -> 1966 | L38: =IF(H38="?",$H$2,H38) -> tier - 3 | M38: =IF(I38="?",$I$2,I38) -> tier - 1 | N38: =IF(J38="?","UNKNOWN",J38) -> R1012 | O38: =IFERROR(INT(YEARFRAC(E38, DATE(2023,6,8))), "") -> 56 | P38: 24272
A39: Id965 | B39: 1965 | C39: Jun | D39: 23 | E39: =DATE(K39, MONTH(1 & C39), D39) -> 23916 | F39: 0 | G39: 11455.28 | H39: tier - 3 | I39: tier - 2 | J39: R1011 | K39: =IF(B39="?",ROUND(AVERAGE($B$2:$B$2344),0),B39) -> 1965 | L39: =IF(H39="?",$H$2,H39) -> tier - 3 | M39: =IF(I39="?",$I$2,I39) -> tier - 2 | N39: =IF(J39="?","UNKNOWN",J39) -> R1011 | O39: =IFERROR(INT(YEARFRAC(E39, DATE(2023,6,8))), "") -> 57 | P39: 23916
A40: Id964 | B40: 1966 | C40: Sep | D40: 7 | E40: =DATE(K40, MONTH(1 & C40), D40) -> 24357 | F40: 0 | G40: 11478.14 | H40: tier - 3 | I40: tier - 2 | J40: R1025 | K40: =IF(B40="?",ROUND(AVERAGE($B$2:$B$2344),0),B40) -> 1966 | L40: =IF(H40="?",$H$2,H40) -> tier - 3 | M40: =IF(I40="?",$I$2,I40) -> tier - 2 | N40: =IF(J40="?","UNKNOWN",J40) -> R1025 | O40: =IFERROR(INT(YEARFRAC(E40, DATE(2023,6,8))), "") -> 56 | P40: 24357
... A867: Id2322 | B867: 2002 | C867: Sep | D867: 19 | E867: =DATE(K867, MONTH(1 & C867), D867) -> 37518 | F867: 0 | G867: 750 | H867: tier - 3 | I867: tier - 1 | J867: R1012 | K867: =IF(B867="?",ROUND(AVERAGE($B$2:$B$2344),0),B867) -> 2002 | L867: =IF(H867="?",$H$2,H867) -> tier - 3 | M867: =IF(I867="?",$I$2,I867) -> tier - 1 | N867: =IF(J867="?","UNKNOWN",J867) -> R1012 | O867: =IFERROR(INT(YEARFRAC(E867, DATE(2023,6,8))), "") -> 20 | P867: 37518
A868: Id2321 | B868: 1993 | C868: Aug | E868: =DATE(K868, MONTH(1 & C868), D868) -> 34181 | F868: 0 | G868: 760 | H868: tier - 3 | I868: tier - 1 | J868: R1013 | K868: =IF(B868="?",ROUND(AVERAGE($B$2:$B$2344),0),B868) -> 1993 | L868: =IF(H868="?",$H$2,H868) -> tier - 3 | M868: =IF(I868="?",$I$2,I868) -> tier - 1 | N868: =IF(J868="?","UNKNOWN",J868) -> R1013 | O868: =IFERROR(INT(YEARFRAC(E868, DATE(2023,6,8))), "") -> 29 | P868: 34181
A869: Id2320 | B869: 1996 | C869: Oct | D869: 22 | E869: =DATE(K869, MONTH(1 & C869), D869) -> 35360 | F869: 0 | G869: 760 | H869: tier - 3 | I869: tier - 3 | J869: R1013 | K869: =IF(B869="?",ROUND(AVERAGE($B$2:$B$2344),0),B869) -> 1996 | L869: =IF(H869="?",$H$2,H869) -> tier - 3 | M869: =IF(I869="?",$I$2,I869) -> tier - 3 | N869: =IF(J869="?","UNKNOWN",J869) -> R1013 | O869: =IFERROR(INT(YEARFRAC(E869, DATE(2023,6,8))), "") -> 26 | P869: 35360
A870: Id232 | B870: 1995 | C870: Dec | D870: 27 | E870: =DATE(K870, MONTH(1 & C870), D870) -> 35060 | F870: 1 | G870: 34806.47 | H870: tier - 1 | I870: tier - 2 | J870: R1013 | K870: =IF(B870="?",ROUND(AVERAGE($B$2:$B$2344),0),B870) -> 1995 | L870: =IF(H870="?",$H$2,H870) -> tier - 1 | M870: =IF(I870="?",$I$2,I870) -> tier - 2 | N870: =IF(J870="?","UNKNOWN",J870) -> R1013 | O870: =IFERROR(INT(YEARFRAC(E870, DATE(2023,6,8))), "") -> 27 | P870: 35060
A871: Id2319 | B871: 1993 | C871: Jun | D871: 28 | E871: =DATE(K871, MONTH(1 & C871), D871) -> 34148 | F871: 0 | G871: 770 | H871: tier - 3 | I871: tier - 3 | J871: R1013 | K871: =IF(B871="?",ROUND(AVERAGE($B$2:$B$2344),0),B871) -> 1993 | L871: =IF(H871="?",$H$2,H871) -> tier - 3 | M871: =IF(I871="?",$I$2,I871) -> tier - 3 | N871: =IF(J871="?","UNKNOWN",J871) -> R1013 | O871: =IFERROR(INT(YEARFRAC(E871, DATE(2023,6,8))), "") -> 29 | P871: 34148
A872: Id2318 | B872: 1996 | C872: Sep | D872: 18 | E872: =DATE(K872, MONTH(1 & C872), D872) -> 35326 | F872: 0 | G872: 770.38 | H872: tier - 3 | I872: ? | J872: R1012 | K872: =IF(B872="?",ROUND(AVERAGE($B$2:$B$2344),0),B872) -> 1996 | L872: =IF(H872="?",$H$2,H872) -> tier - 3 | M872: =IF(I872="?",$I$2,I872) -> tier - 1 | N872: =IF(J872="?","UNKNOWN",J872) -> R1012 | O872: =IFERROR(INT(YEARFRAC(E872, DATE(2023,6,8))), "") -> 26 | P872: 35326
A873: Id2317 | B873: 1995 | C873: Dec | D873: 7 | E873: =DATE(K873, MONTH(1 & C873), D873) -> 35040 | F873: 0 | G873: 773.54 | H873: tier - 3 | I873: tier - 2 | J873: R1013 | K873: =IF(B873="?",ROUND(AVERAGE($B$2:$B$2344),0),B873) -> 1995 | L873: =IF(H873="?",$H$2,H873) -> tier - 3 | M873: =IF(I873="?",$I$2,I873) -> tier - 2 | N873: =IF(J873="?","UNKNOWN",J873) -> R1013 | O873: =IFERROR(INT(YEARFRAC(E873, DATE(2023,6,8))), "") -> 27 | P873: 35040
A874: Id2316 | B874: 2004 | C874: Oct | D874: 7 | E874: =DATE(K874, MONTH(1 & C874), D874) -> 38267 | F874: 0 | G874: 830.52 | H874: tier - 3 | I874: tier - 2 | J874: R1011 | K874: =IF(B874="?",ROUND(AVERAGE($B$2:$B$2344),0),B874) -> 2004 | L874: =IF(H874="?",$H$2,H874) -> tier - 3 | M874: =IF(I874="?",$I$2,I874) -> tier - 2 | N874: =IF(J874="?","UNKNOWN",J874) -> R1011 | O874: =IFERROR(INT(YEARFRAC(E874, DATE(2023,6,8))), "") -> 18 | P874: 38267
A875: Id2315 | B875: 2000 | C875: Nov | D875: 18 | E875: =DATE(K875, MONTH(1 & C875), D875) -> 36848 | F875: 0 | G875: 865.41 | H875: tier - 3 | I875: tier - 1 | J875: R1013 | K875: =IF(B875="?",ROUND(AVERAGE($B$2:$B$2344),0),B875) -> 2000 | L875: =IF(H875="?",$H$2,H875) -> tier - 3 | M875: =IF(I875="?",$I$2,I875) -> tier - 1 | N875: =IF(J875="?","UNKNOWN",J875) -> R1013 | O875: =IFERROR(INT(YEARFRAC(E875, DATE(2023,6,8))), "") -> 22 | P875: 36848
A876: Id2314 | B876: 1993 | C876: Nov | D876: 27 | E876: =DATE(K876, MONTH(1 & C876), D876) -> 34300 | F876: 0 | G876: 896.21 | H876: tier - 3 | I876: tier - 1 | J876: R1013 | K876: =IF(B876="?",ROUND(AVERAGE($B$2:$B$2344),0),B876) -> 1993 | L876: =IF(H876="?",$H$2,H876) -> tier - 3 | M876: =IF(I876="?",$I$2,I876) -> tier - 1 | N876: =IF(J876="?","UNKNOWN",J876) -> R1013 | O876: =IFERROR(INT(YEARFRAC(E876, DATE(2023,6,8))), "") -> 29 | P876: 34300
A877: Id2313 | B877: 1994 | C877: Oct | D877: 30 | E877: =DATE(K877, MONTH(1 & C877), D877) -> 34637 | F877: 0 | G877: 915.07 | H877: tier - 3 | I877: tier - 1 | J877: R1013 | K877: =IF(B877="?",ROUND(AVERAGE($B$2:$B$2344),0),B877) -> 1994 | L877: =IF(H877="?",$H$2,H877) -> tier - 3 | M877: =IF(I877="?",$I$2,I877) -> tier - 1 | N877: =IF(J877="?","UNKNOWN",J877) -> R1013 | O877: =IFERROR(INT(YEARFRAC(E877, DATE(2023,6,8))), "") -> 28 | P877: 34637
A878: Id2312 | B878: 1995 | C878: Oct | D878: 28 | E878: =DATE(K878, MONTH(1 & C878), D878) -> 35000 | F878: 0 | G878: 928.59 | H878: tier - 3 | I878: tier - 1 | J878: R1013 | K878: =IF(B878="?",ROUND(AVERAGE($B$2:$B$2344),0),B878) -> 1995 | L878: =IF(H878="?",$H$2,H878) -> tier - 3 | M878: =IF(I878="?",$I$2,I878) -> tier - 1 | N878: =IF(J878="?","UNKNOWN",J878) -> R1013 | O878: =IFERROR(INT(YEARFRAC(E878, DATE(2023,6,8))), "") -> 27 | P878: 35000
A879: Id2311 | B879: 2001 | C879: Aug | D879: 19 | E879: =DATE(K879, MONTH(1 & C879), D879) -> 37122 | F879: 0 | G879: 964.71 | H879: tier - 3 | I879: tier - 2 | J879: R1013 | K879: =IF(B879="?",ROUND(AVERAGE($B$2:$B$2344),0),B879) -> 2001 | L879: =IF(H879="?",$H$2,H879) -> tier - 3 | M879: =IF(I879="?",$I$2,I879) -> tier - 2 | N879: =IF(J879="?","UNKNOWN",J879) -> R1013 | O879: =IFERROR(INT(YEARFRAC(E879, DATE(2023,6,8))), "") -> 21 | P879: 37122
A880: Id2310 | B880: 1994 | C880: Nov | D880: 22 | E880: =DATE(K880, MONTH(1 & C880), D880) -> 34660 | F880: 0 | G880: 1006.65 | H880: tier - 3 | I880: tier - 2 | J880: R1013 | K880: =IF(B880="?",ROUND(AVERAGE($B$2:$B$2344),0),B880) -> 1994 | L880: =IF(H880="?",$H$2,H880) -> tier - 3 | M880: =IF(I880="?",$I$2,I880) -> tier - 2 | N880: =IF(J880="?","UNKNOWN",J880) -> R1013 | O880: =IFERROR(INT(YEARFRAC(E880, DATE(2023,6,8))), "") -> 28 | P880: 34660
... A2015: Id129 | B2015: 1985 | C2015: Sep | D2015: 20 | E2015: =DATE(K2015, MONTH(1 & C2015), D2015) -> 31310 | F2015: 1 | G2015: 39047.29 | H2015: tier - 1 | I2015: tier - 3 | J2015: R1017 | K2015: =IF(B2015="?",ROUND(AVERAGE($B$2:$B$2344),0),B2015) -> 1985 | L2015: =IF(H2015="?",$H$2,H2015) -> tier - 1 | M2015: =IF(I2015="?",$I$2,I2015) -> tier - 3 | N2015: =IF(J2015="?","UNKNOWN",J2015) -> R1017 | O2015: =IFERROR(INT(YEARFRAC(E2015, DATE(2023,6,8))), "") -> 37 | P2015: 31310
A2016: Id1289 | B2016: ? | C2016: Jul | D2016: 24 | E2016: =DATE(K2016, MONTH(1 & C2016), D2016) -> 30521 | F2016: 0 | G2016: 8534.67 | H2016: tier - 2 | I2016: tier - 3 | J2016: R1024 | K2016: =IF(B2016="?",ROUND(AVERAGE($B$2:$B$2344),0),B2016) -> 1983 | L2016: =IF(H2016="?",$H$2,H2016) -> tier - 2 | M2016: =IF(I2016="?",$I$2,I2016) -> tier - 3 | N2016: =IF(J2016="?","UNKNOWN",J2016) -> R1024 | O2016: =IFERROR(INT(YEARFRAC(E2016, DATE(2023,6,8))), "") -> 39 | P2016: 30521
A2017: Id1288 | B2017: 1981 | C2017: Dec | D2017: 27 | E2017: =DATE(K2017, MONTH(1 & C2017), D2017) -> 29947 | F2017: 3 | G2017: 8538.29 | H2017: tier - 2 | I2017: tier - 3 | J2017: R1024 | K2017: =IF(B2017="?",ROUND(AVERAGE($B$2:$B$2344),0),B2017) -> 1981 | L2017: =IF(H2017="?",$H$2,H2017) -> tier - 2 | M2017: =IF(I2017="?",$I$2,I2017) -> tier - 3 | N2017: =IF(J2017="?","UNKNOWN",J2017) -> R1024 | O2017: =IFERROR(INT(YEARFRAC(E2017, DATE(2023,6,8))), "") -> 41 | P2017: 29947
A2018: Id1287 | B2018: 1975 | C2018: Nov | D2018: 6 | E2018: =DATE(K2018, MONTH(1 & C2018), D2018) -> 27704 | F2018: 1 | G2018: 8539.67 | H2018: tier - 2 | I2018: tier - 3 | J2018: R1011 | K2018: =IF(B2018="?",ROUND(AVERAGE($B$2:$B$2344),0),B2018) -> 1975 | L2018: =IF(H2018="?",$H$2,H2018) -> tier - 2 | M2018: =IF(I2018="?",$I$2,I2018) -> tier - 3 | N2018: =IF(J2018="?","UNKNOWN",J2018) -> R1011 | O2018: =IFERROR(INT(YEARFRAC(E2018, DATE(2023,6,8))), "") -> 47 | P2018: 27704
A2019: Id1286 | B2019: ? | C2019: Dec | D2019: 12 | E2019: =DATE(K2019, MONTH(1 & C2019), D2019) -> 30662 | F2019: 1 | G2019: 8547.69 | H2019: tier - 2 | I2019: tier - 1 | J2019: R1013 | K2019: =IF(B2019="?",ROUND(AVERAGE($B$2:$B$2344),0),B2019) -> 1983 | L2019: =IF(H2019="?",$H$2,H2019) -> tier - 2 | M2019: =IF(I2019="?",$I$2,I2019) -> tier - 1 | N2019: =IF(J2019="?","UNKNOWN",J2019) -> R1013 | O2019: =IFERROR(INT(YEARFRAC(E2019, DATE(2023,6,8))), "") -> 39 | P2019: 30662
A2020: Id1285 | B2020: 1975 | C2020: Aug | D2020: 6 | E2020: =DATE(K2020, MONTH(1 & C2020), D2020) -> 27612 | F2020: 1 | G2020: 8551.35 | H2020: tier - 2 | I2020: tier - 2 | J2020: R1011 | K2020: =IF(B2020="?",ROUND(AVERAGE($B$2:$B$2344),0),B2020) -> 1975 | L2020: =IF(H2020="?",$H$2,H2020) -> tier - 2 | M2020: =IF(I2020="?",$I$2,I2020) -> tier - 2 | N2020: =IF(J2020="?","UNKNOWN",J2020) -> R1011 | O2020: =IFERROR(INT(YEARFRAC(E2020, DATE(2023,6,8))), "") -> 47 | P2020: 27612
A2021: Id1284 | B2021: 1975 | C2021: Aug | D2021: 21 | E2021: =DATE(K2021, MONTH(1 & C2021), D2021) -> 27627 | F2021: 1 | G2021: 8556.91 | H2021: tier - 2 | I2021: tier - 1 | J2021: R1011 | K2021: =IF(B2021="?",ROUND(AVERAGE($B$2:$B$2344),0),B2021) -> 1975 | L2021: =IF(H2021="?",$H$2,H2021) -> tier - 2 | M2021: =IF(I2021="?",$I$2,I2021) -> tier - 1 | N2021: =IF(J2021="?","UNKNOWN",J2021) -> R1011 | O2021: =IFERROR(INT(YEARFRAC(E2021, DATE(2023,6,8))), "") -> 47 | P2021: 27627
A2022: Id1283 | B2022: 1988 | C2022: Sep | D2022: 21 | E2022: =DATE(K2022, MONTH(1 & C2022), D2022) -> 32407 | F2022: 3 | G2022: 8567.25 | H2022: tier - 2 | I2022: tier - 1 | J2022: R1012 | K2022: =IF(B2022="?",ROUND(AVERAGE($B$2:$B$2344),0),B2022) -> 1988 | L2022: =IF(H2022="?",$H$2,H2022) -> tier - 2 | M2022: =IF(I2022="?",$I$2,I2022) -> tier - 1 | N2022: =IF(J2022="?","UNKNOWN",J2022) -> R1012 | O2022: =IFERROR(INT(YEARFRAC(E2022, DATE(2023,6,8))), "") -> 34 | P2022: 32407
A2023: Id1282 | B2023: 1975 | C2023: Sep | D2023: 26 | E2023: =DATE(K2023, MONTH(1 & C2023), D2023) -> 27663 | F2023: 1 | G2023: 8569.86 | H2023: tier - 2 | I2023: tier - 3 | J2023: R1013 | K2023: =IF(B2023="?",ROUND(AVERAGE($B$2:$B$2344),0),B2023) -> 1975 | L2023: =IF(H2023="?",$H$2,H2023) -> tier - 2 | M2023: =IF(I2023="?",$I$2,I2023) -> tier - 3 | N2023: =IF(J2023="?","UNKNOWN",J2023) -> R1013 | O2023: =IFERROR(INT(YEARFRAC(E2023, DATE(2023,6,8))), "") -> 47 | P2023: 27663
A2024: Id1281 | B2024: 1982 | C2024: Dec | D2024: 6 | E2024: =DATE(K2024, MONTH(1 & C2024), D2024) -> 30291 | F2024: 3 | G2024: 8572.04 | H2024: tier - 2 | I2024: tier - 2 | J2024: R1021 | K2024: =IF(B2024="?",ROUND(AVERAGE($B$2:$B$2344),0),B2024) -> 1982 | L2024: =IF(H2024="?",$H$2,H2024) -> tier - 2 | M2024: =IF(I2024="?",$I$2,I2024) -> tier - 2 | N2024: =IF(J2024="?","UNKNOWN",J2024) -> R1021 | O2024: =IFERROR(INT(YEARFRAC(E2024, DATE(2023,6,8))), "") -> 40 | P2024: 30291
A2025: Id1280 | B2025: 1987 | C2025: Nov | D2025: 11 | E2025: =DATE(K2025, MONTH(1 & C2025), D2025) -> 32092 | F2025: 3 | G2025: 8573.3 | H2025: tier - 2 | I2025: tier - 2 | J2025: R1021 | K2025: =IF(B2025="?",ROUND(AVERAGE($B$2:$B$2344),0),B2025) -> 1987 | L2025: =IF(H2025="?",$H$2,H2025) -> tier - 2 | M2025: =IF(I2025="?",$I$2,I2025) -> tier - 2 | N2025: =IF(J2025="?","UNKNOWN",J2025) -> R1021 | O2025: =IFERROR(INT(YEARFRAC(E2025, DATE(2023,6,8))), "") -> 35 | P2025: 32092
A2026: Id128 | B2026: 1982 | C2026: Aug | D2026: 4 | E2026: =DATE(K2026, MONTH(1 & C2026), D2026) -> 30167 | F2026: 1 | G2026: 39125.33 | H2026: tier - 1 | I2026: tier - 1 | J2026: R1016 | K2026: =IF(B2026="?",ROUND(AVERAGE($B$2:$B$2344),0),B2026) -> 1982 | L2026: =IF(H2026="?",$H$2,H2026) -> tier - 1 | M2026: =IF(I2026="?",$I$2,I2026) -> tier - 1 | N2026: =IF(J2026="?","UNKNOWN",J2026) -> R1016 | O2026: =IFERROR(INT(YEARFRAC(E2026, DATE(2023,6,8))), "") -> 40 | P2026: 30167
A2027: Id1279 | B2027: 1983 | C2027: Dec | D2027: 30 | E2027: =DATE(K2027, MONTH(1 & C2027), D2027) -> 30680 | F2027: 5 | G2027: 8582.3 | H2027: tier - 2 | I2027: tier - 1 | J2027: R1013 | K2027: =IF(B2027="?",ROUND(AVERAGE($B$2:$B$2344),0),B2027) -> 1983 | L2027: =IF(H2027="?",$H$2,H2027) -> tier - 2 | M2027: =IF(I2027="?",$I$2,I2027) -> tier - 1 | N2027: =IF(J2027="?","UNKNOWN",J2027) -> R1013 | O2027: =IFERROR(INT(YEARFRAC(E2027, DATE(2023,6,8))), "") -> 39 | P2027: 30680
A2028: Id1278 | B2028: 1983 | C2028: Jul | D2028: 25 | E2028: =DATE(K2028, MONTH(1 & C2028), D2028) -> 30522 | F2028: 5 | G2028: 8596.83 | H2028: tier - 2 | I2028: tier - 3 | J2028: R1013 | K2028: =IF(B2028="?",ROUND(AVERAGE($B$2:$B$2344),0),B2028) -> 1983 | L2028: =IF(H2028="?",$H$2,H2028) -> tier - 2 | M2028: =IF(I2028="?",$I$2,I2028) -> tier - 3 | N2028: =IF(J2028="?","UNKNOWN",J2028) -> R1013 | O2028: =IFERROR(INT(YEARFRAC(E2028, DATE(2023,6,8))), "") -> 39 | P2028: 30522
A2029: Id1277 | B2029: 1973 | C2029: Jul | D2029: 11 | E2029: =DATE(K2029, MONTH(1 & C2029), D2029) -> 26856 | F2029: 0 | G2029: 8601.33 | H2029: tier - 2 | I2029: tier - 1 | J2029: R1013 | K2029: =IF(B2029="?",ROUND(AVERAGE($B$2:$B$2344),0),B2029) -> 1973 | L2029: =IF(H2029="?",$H$2,H2029) -> tier - 2 | M2029: =IF(I2029="?",$I$2,I2029) -> tier - 1 | N2029: =IF(J2029="?","UNKNOWN",J2029) -> R1013 | O2029: =IFERROR(INT(YEARFRAC(E2029, DATE(2023,6,8))), "") -> 49 | P2029: 26856
A2030: Id1276 | B2030: 1977 | C2030: Sep | D2030: 24 | E2030: =DATE(K2030, MONTH(1 & C2030), D2030) -> 28392 | F2030: 2 | G2030: 8603.82 | H2030: tier - 2 | I2030: tier - 1 | J2030: R1019 | K2030: =IF(B2030="?",ROUND(AVERAGE($B$2:$B$2344),0),B2030) -> 1977 | L2030: =IF(H2030="?",$H$2,H2030) -> tier - 2 | M2030: =IF(I2030="?",$I$2,I2030) -> tier - 1 | N2030: =IF(J2030="?","UNKNOWN",J2030) -> R1019 | O2030: =IFERROR(INT(YEARFRAC(E2030, DATE(2023,6,8))), "") -> 45 | P2030: 28392
A2031: Id1275 | B2031: 1977 | C2031: Nov | D2031: 12 | E2031: =DATE(K2031, MONTH(1 & C2031), D2031) -> 28441 | F2031: 2 | G2031: 8604.48 | H2031: tier - 3 | I2031: tier - 2 | J2031: R1016 | K2031: =IF(B2031="?",ROUND(AVERAGE($B$2:$B$2344),0),B2031) -> 1977 | L2031: =IF(H2031="?",$H$2,H2031) -> tier - 3 | M2031: =IF(I2031="?",$I$2,I2031) -> tier - 2 | N2031: =IF(J2031="?","UNKNOWN",J2031) -> R1016 | O2031: =IFERROR(INT(YEARFRAC(E2031, DATE(2023,6,8))), "") -> 45 | P2031: 28441
... A2344: ? | B2344: 2004 | C2344: Nov | D2344: 6 | E2344: =DATE(K2344, MONTH(1 & C2344), D2344) -> 38297 | F2344: 0 | G2344: 1137.01 | H2344: tier - 3 | I2344: tier - 1 | J2344: R1013 | K2344: =IF(B2344="?",ROUND(AVERAGE($B$2:$B$2344),0),B2344) -> 2004 | L2344: =IF(H2344="?",$H$2,H2344) -> tier - 3 | M2344: =IF(I2344="?",$I$2,I2344) -> tier - 1 | N2344: =IF(J2344="?","UNKNOWN",J2344) -> R1013 | O2344: =IFERROR(INT(YEARFRAC(E2344, DATE(2023,6,8))), "") -> 18 | P2344: 38297

Sheet Pivot table
A2: Total customers count, | C2: Total hospitalisation count, | F2: Total healthcare costs, | I2: Average costs and medical metrics
A3: Count of Customer | C3: Row Labels | D3: Count of Hospital Tier | F3: Row Labels | G3: Sum of Charges | I3: Row Labels | J3: Average of Charges
A4: 2335 | C4: tier - 1 | D4: 305 | F4: tier - 1 | G4: 9159976.4 | I4: tier - 1 | J4: 30032.709
C5: tier - 2 | D5: 1336 | F5: tier - 2 | G5: 15874466 | I5: tier - 2 | J5: 11882.085
C6: tier - 3 | D6: 693 | F6: tier - 3 | G6: 6557352.6 | I6: tier - 3 | J6: 9462.2693
C7: Grand Total | D7: 2334 | F7: Grand Total | G7: 31591795 | I7: Grand Total | J7: 13535.473

Sheet Healthcare
A1: Customer id | B1: First Name | C1: BMI | D1: HBA1C | E1: Heart Issues | F1: Any Transplants | G1: Cancer History | H1: Number Of Major Surgeries | I1: Smoker | J1: Weight Status | K1: Date Of Birth | L1: Charges | M1: Hospital Tier | N1: City Tier | O1: State ID | P1: Age
A2: Id1 | B2: =VLOOKUP($A2,'Customer Names'!$A:$D,3, FALSE) -> Hawks | C2: =VLOOKUP($A2,'Medical Examinations'!$A:$D, 2, FALSE) -> 47.41 | D2: =VLOOKUP($A2, 'Medical Examinations'!$A:$D,3, FALSE) -> 7.47 | E2: =VLOOKUP($A2, 'Medical Examinations'!$A:$D, 4, FALSE) -> No | F2: =VLOOKUP($A2, 'Medical Examinations'!$A:$J, 5, FALSE) -> No | G2: =VLOOKUP($A2, 'Medical Examinations'!$A:$I, 6, FALSE) -> No | H2: =VLOOKUP($A2,'Medical Examinations'!$A:$L,10, FALSE) -> 0 | I2: =VLOOKUP($A2, 'Medical Examinations'!$A:$J, 9, FALSE) -> Yes | J2: =VLOOKUP($A2, 'Medical Examinations'!$A:$P, 11, FALSE) -> OBESITY | K2: 31401 | L2: =VLOOKUP($A2, 'Hospitalisation Details'!$A:$H, 7, FALSE) -> 63770.43 | M2: =VLOOKUP($A2, 'Hospitalisation Details'!$A:$L, 12, FALSE) -> tier - 1 | N2: =VLOOKUP($A2, 'Hospitalisation Details'!$A:$M, 13, FALSE) -> tier - 3 | O2: =VLOOKUP($A2, 'Hospitalisation Details'!$A:$N, 14, FALSE) -> R1013 | P2: =VLOOKUP($A2, 'Hospitalisation Details'!$A:$O, 15, FALSE) -> 54
A3: Id2 | B3: =VLOOKUP($A3,'Customer Names'!$A:$D,3, FALSE) -> Lehner | C3: =VLOOKUP($A3,'Medical Examinations'!$A:$D, 2, FALSE) -> 30.36 | D3: =VLOOKUP($A3, 'Medical Examinations'!$A:$D,3, FALSE) -> 5.77 | E3: =VLOOKUP($A3, 'Medical Examinations'!$A:$D, 4, FALSE) -> No | F3: =VLOOKUP($A3, 'Medical Examinations'!$A:$J, 5, FALSE) -> No | G3: =VLOOKUP($A3, 'Medical Examinations'!$A:$I, 6, FALSE) -> No | H3: =VLOOKUP($A3,'Medical Examinations'!$A:$L,10, FALSE) -> 0 | I3: =VLOOKUP($A3, 'Medical Examinations'!$A:$J, 9, FALSE) -> Yes | J3: =VLOOKUP($A3, 'Medical Examinations'!$A:$P, 11, FALSE) -> OBESITY | K3: 33564 | L3: =VLOOKUP($A3, 'Hospitalisation Details'!$A:$H, 7, FALSE) -> 62592.87 | M3: =VLOOKUP($A3, 'Hospitalisation Details'!$A:$L, 12, FALSE) -> tier - 2 | N3: =VLOOKUP($A3, 'Hospitalisation Details'!$A:$M, 13, FALSE) -> tier - 3 | O3: =VLOOKUP($A3, 'Hospitalisation Details'!$A:$N, 14, FALSE) -> R1013 | P3: =VLOOKUP($A3, 'Hospitalisation Details'!$A:$O, 15, FALSE) -> 46
A4: Id3 | B4: =VLOOKUP($A4,'Customer Names'!$A:$D,3, FALSE) -> Lu | C4: =VLOOKUP($A4,'Medical Examinations'!$A:$D, 2, FALSE) -> 34.485 | D4: =VLOOKUP($A4, 'Medical Examinations'!$A:$D,3, FALSE) -> 11.87 | E4: =VLOOKUP($A4, 'Medical Examinations'!$A:$D, 4, FALSE) -> Yes | F4: =VLOOKUP($A4, 'Medical Examinations'!$A:$J, 5, FALSE) -> No | G4: =VLOOKUP($A4, 'Medical Examinations'!$A:$I, 6, FALSE) -> No | H4: =VLOOKUP($A4,'Medical Examinations'!$A:$L,10, FALSE) -> 2 | I4: =VLOOKUP($A4, 'Medical Examinations'!$A:$J, 9, FALSE) -> Yes | J4: =VLOOKUP($A4, 'Medical Examinations'!$A:$P, 11, FALSE) -> OBESITY | K4: 33883 | L4: =VLOOKUP($A4, 'Hospitalisation Details'!$A:$H, 7, FALSE) -> 60021.4 | M4: =VLOOKUP($A4, 'Hospitalisation Details'!$A:$L, 12, FALSE) -> tier - 1 | N4: =VLOOKUP($A4, 'Hospitalisation Details'!$A:$M, 13, FALSE) -> tier - 1 | O4: =VLOOKUP($A4, 'Hospitalisation Details'!$A:$N, 14, FALSE) -> R1012 | P4: =VLOOKUP($A4, 'Hospitalisation Details'!$A:$O, 15, FALSE) -> 52 | R4: Healthcare statistics
A5: Id4 | B5: =VLOOKUP($A5,'Customer Names'!$A:$D,3, FALSE) -> Osborne | C5: =VLOOKUP($A5,'Medical Examinations'!$A:$D, 2, FALSE) -> 38.095 | D5: =VLOOKUP($A5, 'Medical Examinations'!$A:$D,3, FALSE) -> 6.05 | E5: =VLOOKUP($A5, 'Medical Examinations'!$A:$D, 4, FALSE) -> No | F5: =VLOOKUP($A5, 'Medical Examinations'!$A:$J, 5, FALSE) -> No | G5: =VLOOKUP($A5, 'Medical Examinations'!$A:$I, 6, FALSE) -> No | H5: =VLOOKUP($A5,'Medical Examinations'!$A:$L,10, FALSE) -> 0 | I5: =VLOOKUP($A5, 'Medical Examinations'!$A:$J, 9, FALSE) -> Yes | J5: =VLOOKUP($A5, 'Medical Examinations'!$A:$P, 11, FALSE) -> OBESITY | K5: 36320 | L5: =VLOOKUP($A5, 'Hospitalisation Details'!$A:$H, 7, FALSE) -> 58571.07 | M5: =VLOOKUP($A5, 'Hospitalisation Details'!$A:$L, 12, FALSE) -> tier - 1 | N5: =VLOOKUP($A5, 'Hospitalisation Details'!$A:$M, 13, FALSE) -> tier - 3 | O5: =VLOOKUP($A5, 'Hospitalisation Details'!$A:$N, 14, FALSE) -> R1024 | P5: =VLOOKUP($A5, 'Hospitalisation Details'!$A:$O, 15, FALSE) -> 32 | R5: Total customers count | S5: =SUBTOTAL(103,Healthcare!$A$2:$A$2335) -> 2334
A6: Id5 | B6: =VLOOKUP($A6,'Customer Names'!$A:$D,3, FALSE) -> Kadala | C6: =VLOOKUP($A6,'Medical Examinations'!$A:$D, 2, FALSE) -> 35.53 | D6: =VLOOKUP($A6, 'Medical Examinations'!$A:$D,3, FALSE) -> 5.45 | E6: =VLOOKUP($A6, 'Medical Examinations'!$A:$D, 4, FALSE) -> No | F6: =VLOOKUP($A6, 'Medical Examinations'!$A:$J, 5, FALSE) -> No | G6: =VLOOKUP($A6, 'Medical Examinations'!$A:$I, 6, FALSE) -> No | H6: =VLOOKUP($A6,'Medical Examinations'!$A:$L,10, FALSE) -> 0 | I6: =VLOOKUP($A6, 'Medical Examinations'!$A:$J, 9, FALSE) -> Yes | J6: =VLOOKUP($A6, 'Medical Examinations'!$A:$P, 11, FALSE) -> OBESITY | K6: 36812 | L6: =VLOOKUP($A6, 'Hospitalisation Details'!$A:$H, 7, FALSE) -> 55135.4 | M6: =VLOOKUP($A6, 'Hospitalisation Details'!$A:$L, 12, FALSE) -> tier - 1 | N6: =VLOOKUP($A6, 'Hospitalisation Details'!$A:$M, 13, FALSE) -> tier - 2 | O6: =VLOOKUP($A6, 'Hospitalisation Details'!$A:$N, 14, FALSE) -> R1012 | P6: =VLOOKUP($A6, 'Hospitalisation Details'!$A:$O, 15, FALSE) -> 33 | R6: Total hospitalisation count | S6: =SUBTOTAL(103,Healthcare!$B$2:$B$2335) -> 2334
A7: Id6 | B7: =VLOOKUP($A7,'Customer Names'!$A:$D,3, FALSE) -> Baker | C7: =VLOOKUP($A7,'Medical Examinations'!$A:$D, 2, FALSE) -> 32.8 | D7: =VLOOKUP($A7, 'Medical Examinations'!$A:$D,3, FALSE) -> 6.59 | E7: =VLOOKUP($A7, 'Medical Examinations'!$A:$D, 4, FALSE) -> No | F7: =VLOOKUP($A7, 'Medical Examinations'!$A:$J, 5, FALSE) -> No | G7: =VLOOKUP($A7, 'Medical Examinations'!$A:$I, 6, FALSE) -> No | H7: =VLOOKUP($A7,'Medical Examinations'!$A:$L,10, FALSE) -> 0 | I7: =VLOOKUP($A7, 'Medical Examinations'!$A:$J, 9, FALSE) -> Yes | J7: =VLOOKUP($A7, 'Medical Examinations'!$A:$P, 11, FALSE) -> OBESITY | K7: 38297 | L7: =VLOOKUP($A7, 'Hospitalisation Details'!$A:$H, 7, FALSE) -> 52590.83 | M7: =VLOOKUP($A7, 'Hospitalisation Details'!$A:$L, 12, FALSE) -> tier - 1 | N7: =VLOOKUP($A7, 'Hospitalisation Details'!$A:$M, 13, FALSE) -> tier - 3 | O7: =VLOOKUP($A7, 'Hospitalisation Details'!$A:$N, 14, FALSE) -> R1011 | P7: =VLOOKUP($A7, 'Hospitalisation Details'!$A:$O, 15, FALSE) -> 60 | R7: Total healthcare costs | S7: =SUBTOTAL(109,Healthcare!$L$2:$L$2335) -> 31591795
A8: Id7 | B8: =VLOOKUP($A8,'Customer Names'!$A:$D,3, FALSE) -> Macpherson | C8: =VLOOKUP($A8,'Medical Examinations'!$A:$D, 2, FALSE) -> 36.4 | D8: =VLOOKUP($A8, 'Medical Examinations'!$A:$D,3, FALSE) -> 6.07 | E8: =VLOOKUP($A8, 'Medical Examinations'!$A:$D, 4, FALSE) -> No | F8: =VLOOKUP($A8, 'Medical Examinations'!$A:$J, 5, FALSE) -> No | G8: =VLOOKUP($A8, 'Medical Examinations'!$A:$I, 6, FALSE) -> No | H8: =VLOOKUP($A8,'Medical Examinations'!$A:$L,10, FALSE) -> 0 | I8: =VLOOKUP($A8, 'Medical Examinations'!$A:$J, 9, FALSE) -> Yes | J8: =VLOOKUP($A8, 'Medical Examinations'!$A:$P, 11, FALSE) -> OBESITY | K8: 25123 | L8: =VLOOKUP($A8, 'Hospitalisation Details'!$A:$H, 7, FALSE) -> 51194.56 | M8: =VLOOKUP($A8, 'Hospitalisation Details'!$A:$L, 12, FALSE) -> tier - 1 | N8: =VLOOKUP($A8, 'Hospitalisation Details'!$A:$M, 13, FALSE) -> tier - 3 | O8: =VLOOKUP($A8, 'Hospitalisation Details'!$A:$N, 14, FALSE) -> R1011 | P8: =VLOOKUP($A8, 'Hospitalisation Details'!$A:$O, 15, FALSE) -> 28 | R8: Average costs and medical metrics | S8: =SUBTOTAL(101,Healthcare!$L$2:$L$2335) -> 13535.473
A9: Id8 | B9: =VLOOKUP($A9,'Customer Names'!$A:$D,3, FALSE) -> Hallman | C9: =VLOOKUP($A9,'Medical Examinations'!$A:$D, 2, FALSE) -> 36.96 | D9: =VLOOKUP($A9, 'Medical Examinations'!$A:$D,3, FALSE) -> 7.93 | E9: =VLOOKUP($A9, 'Medical Examinations'!$A:$D, 4, FALSE) -> No | F9: =VLOOKUP($A9, 'Medical Examinations'!$A:$J, 5, FALSE) -> No | G9: =VLOOKUP($A9, 'Medical Examinations'!$A:$I, 6, FALSE) -> No | H9: =VLOOKUP($A9,'Medical Examinations'!$A:$L,10, FALSE) -> 3 | I9: =VLOOKUP($A9, 'Medical Examinations'!$A:$J, 9, FALSE) -> Yes | J9: =VLOOKUP($A9, 'Medical Examinations'!$A:$P, 11, FALSE) -> OBESITY | K9: 28853 | L9: =VLOOKUP($A9, 'Hospitalisation Details'!$A:$H, 7, FALSE) -> 49577.66 | M9: =VLOOKUP($A9, 'Hospitalisation Details'!$A:$L, 12, FALSE) -> tier - 2 | N9: =VLOOKUP($A9, 'Hospitalisation Details'!$A:$M, 13, FALSE) -> tier - 2 | O9: =VLOOKUP($A9, 'Hospitalisation Details'!$A:$N, 14, FALSE) -> R1013 | P9: =VLOOKUP($A9, 'Hospitalisation Details'!$A:$O, 15, FALSE) -> 64
A10: Id9 | B10: =VLOOKUP($A10,'Customer Names'!$A:$D,3, FALSE) -> Moran | C10: =VLOOKUP($A10,'Medical Examinations'!$A:$D, 2, FALSE) -> 41.14 | D10: =VLOOKUP($A10, 'Medical Examinations'!$A:$D,3, FALSE) -> 9.58 | E10: =VLOOKUP($A10, 'Medical Examinations'!$A:$D, 4, FALSE) -> Yes | F10: =VLOOKUP($A10, 'Medical Examinations'!$A:$J, 5, FALSE) -> No | G10: =VLOOKUP($A10, 'Medical Examinations'!$A:$I, 6, FALSE) -> Yes | H10: =VLOOKUP($A10,'Medical Examinations'!$A:$L,10, FALSE) -> 1 | I10: =VLOOKUP($A10, 'Medical Examinations'!$A:$J, 9, FALSE) -> Yes | J10: =VLOOKUP($A10, 'Medical Examinations'!$A:$P, 11, FALSE) -> OBESITY | K10: 28303 | L10: =VLOOKUP($A10, 'Hospitalisation Details'!$A:$H, 7, FALSE) -> 48970.25 | M10: =VLOOKUP($A10, 'Hospitalisation Details'!$A:$L, 12, FALSE) -> tier - 1 | N10: =VLOOKUP($A10, 'Hospitalisation Details'!$A:$M, 13, FALSE) -> tier - 2 | O10: =VLOOKUP($A10, 'Hospitalisation Details'!$A:$N, 14, FALSE) -> R1013 | P10: =VLOOKUP($A10, 'Hospitalisation Details'!$A:$O, 15, FALSE) -> 59
A11: Id10 | B11: =VLOOKUP($A11,'Customer Names'!$A:$D,3, FALSE) -> Benner | C11: =VLOOKUP($A11,'Medical Examinations'!$A:$D, 2, FALSE) -> 38.06 | D11: =VLOOKUP($A11, 'Medical Examinations'!$A:$D,3, FALSE) -> 10.79 | E11: =VLOOKUP($A11, 'Medical Examinations'!$A:$D, 4, FALSE) -> No | F11: =VLOOKUP($A11, 'Medical Examinations'!$A:$J, 5, FALSE) -> No | G11: =VLOOKUP($A11, 'Medical Examinations'!$A:$I, 6, FALSE) -> No | H11: =VLOOKUP($A11,'Medical Examinations'!$A:$L,10, FALSE) -> 0 | I11: =VLOOKUP($A11, 'Medical Examinations'!$A:$J, 9, FALSE) -> Yes | J11: =VLOOKUP($A11, 'Medical Examinations'!$A:$P, 11, FALSE) -> OBESITY | K11: 32859 | L11: =VLOOKUP($A11, 'Hospitalisation Details'!$A:$H, 7, FALSE) -> 48885.14 | M11: =VLOOKUP($A11, 'Hospitalisation Details'!$A:$L, 12, FALSE) -> tier - 1 | N11: =VLOOKUP($A11, 'Hospitalisation Details'!$A:$M, 13, FALSE) -> tier - 2 | O11: =VLOOKUP($A11, 'Hospitalisation Details'!$A:$N, 14, FALSE) -> R1013 | P11: =VLOOKUP($A11, 'Hospitalisation Details'!$A:$O, 15, FALSE) -> 44
A12: Id11 | B12: =VLOOKUP($A12,'Customer Names'!$A:$D,3, FALSE) -> Fierr | C12: =VLOOKUP($A12,'Medical Examinations'!$A:$D, 2, FALSE) -> 37.7 | D12: =VLOOKUP($A12, 'Medical Examinations'!$A:$D,3, FALSE) -> 5.96 | E12: =VLOOKUP($A12, 'Medical Examinations'!$A:$D, 4, FALSE) -> Yes | F12: =VLOOKUP($A12, 'Medical Examinations'!$A:$J, 5, FALSE) -> No | G12: =VLOOKUP($A12, 'Medical Examinations'!$A:$I, 6, FALSE) -> No | H12: =VLOOKUP($A12,'Medical Examinations'!$A:$L,10, FALSE) -> 2 | I12: =VLOOKUP($A12, 'Medical Examinations'!$A:$J, 9, FALSE) -> Yes | J12: =VLOOKUP($A12, 'Medical Examinations'!$A:$P, 11, FALSE) -> OBESITY | K12: 25567 | L12: =VLOOKUP($A12, 'Hospitalisation Details'!$A:$H, 7, FALSE) -> 48824.45 | M12: =VLOOKUP($A12, 'Hospitalisation Details'!$A:$L, 12, FALSE) -> tier - 2 | N12: =VLOOKUP($A12, 'Hospitalisation Details'!$A:$M, 13, FALSE) -> tier - 1 | O12: =VLOOKUP($A12, 'Hospitalisation Details'!$A:$N, 14, FALSE) -> R1011 | P12: =VLOOKUP($A12, 'Hospitalisation Details'!$A:$O, 15, FALSE) -> 63
A13: Id12 | B13: =VLOOKUP($A13,'Customer Names'!$A:$D,3, FALSE) -> Franz | C13: =VLOOKUP($A13,'Medical Examinations'!$A:$D, 2, FALSE) -> 42.13 | D13: =VLOOKUP($A13, 'Medical Examinations'!$A:$D,3, FALSE) -> 11.9 | E13: =VLOOKUP($A13, 'Medical Examinations'!$A:$D, 4, FALSE) -> No | F13: =VLOOKUP($A13, 'Medical Examinations'!$A:$J, 5, FALSE) -> No | G13: =VLOOKUP($A13, 'Medical Examinations'!$A:$I, 6, FALSE) -> No | H13: =VLOOKUP($A13,'Medical Examinations'!$A:$L,10, FALSE) -> 0 | I13: =VLOOKUP($A13, 'Medical Examinations'!$A:$J, 9, FALSE) -> Yes | J13: =VLOOKUP($A13, 'Medical Examinations'!$A:$P, 11, FALSE) -> OBESITY | K13: 27939 | L13: =VLOOKUP($A13, 'Hospitalisation Details'!$A:$H, 7, FALSE) -> 48675.52 | M13: =VLOOKUP($A13, 'Hospitalisation Details'!$A:$L, 12, FALSE) -> tier - 1 | N13: =VLOOKUP($A13, 'Hospitalisation Details'!$A:$M, 13, FALSE) -> tier - 2 | O13: =VLOOKUP($A13, 'Hospitalisation Details'!$A:$N, 14, FALSE) -> R1013 | P13: =VLOOKUP($A13, 'Hospitalisation Details'!$A:$O, 15, FALSE) -> 57
A14: Id13 | B14: =VLOOKUP($A14,'Customer Names'!$A:$D,3, FALSE) -> Foster | C14: =VLOOKUP($A14,'Medical Examinations'!$A:$D, 2, FALSE) -> 40.92 | D14: =VLOOKUP($A14, 'Medical Examinations'!$A:$D,3, FALSE) -> 8.41 | E14: =VLOOKUP($A14, 'Medical Examinations'!$A:$D, 4, FALSE) -> No | F14: =VLOOKUP($A14, 'Medical Examinations'!$A:$J, 5, FALSE) -> No | G14: =VLOOKUP($A14, 'Medical Examinations'!$A:$I, 6, FALSE) -> No | H14: =VLOOKUP($A14,'Medical Examinations'!$A:$L,10, FALSE) -> 0 | I14: =VLOOKUP($A14, 'Medical Examinations'!$A:$J, 9, FALSE) -> Yes | J14: =VLOOKUP($A14, 'Medical Examinations'!$A:$P, 11, FALSE) -> OBESITY | K14: 25733 | L14: =VLOOKUP($A14, 'Hospitalisation Details'!$A:$H, 7, FALSE) -> 48673.56 | M14: =VLOOKUP($A14, 'Hospitalisation Details'!$A:$L, 12, FALSE) -> tier - 1 | N14: =VLOOKUP($A14, 'Hospitalisation Details'!$A:$M, 13, FALSE) -> tier - 2 | O14: =VLOOKUP($A14, 'Hospitalisation Details'!$A:$N, 14, FALSE) -> R1013 | P14: =VLOOKUP($A14, 'Hospitalisation Details'!$A:$O, 15, FALSE) -> 60
A15: Id14 | B15: =VLOOKUP($A15,'Customer Names'!$A:$D,3, FALSE) -> Tenorio | C15: =VLOOKUP($A15,'Medical Examinations'!$A:$D, 2, FALSE) -> 40.565 | D15: =VLOOKUP($A15, 'Medical Examinations'!$A:$D,3, FALSE) -> 7.02 | E15: =VLOOKUP($A15, 'Medical Examinations'!$A:$D, 4, FALSE) -> No | F15: =VLOOKUP($A15, 'Medical Examinations'!$A:$J, 5, FALSE) -> No | G15: =VLOOKUP($A15, 'Medical Examinations'!$A:$I, 6, FALSE) -> No | H15: =VLOOKUP($A15,'Medical Examinations'!$A:$L,10, FALSE) -> 0 | I15: =VLOOKUP($A15, 'Medical Examinations'!$A:$J, 9, FALSE) -> Yes | J15: =VLOOKUP($A15, 'Medical Examinations'!$A:$P, 11, FALSE) -> OBESITY | K15: 26545 | L15: =VLOOKUP($A15, 'Hospitalisation Details'!$A:$H, 7, FALSE) -> 48549.18 | M15: =VLOOKUP($A15, 'Hospitalisation Details'!$A:$L, 12, FALSE) -> tier - 1 | N15: =VLOOKUP($A15, 'Hospitalisation Details'!$A:$M, 13, FALSE) -> tier - 3 | O15: =VLOOKUP($A15, 'Hospitalisation Details'!$A:$N, 14, FALSE) -> R1016 | P15: =VLOOKUP($A15, 'Hospitalisation Details'!$A:$O, 15, FALSE) -> 54
A16: Id15 | B16: =VLOOKUP($A16,'Customer Names'!$A:$D,3, FALSE) -> Rios | C16: =VLOOKUP($A16,'Medical Examinations'!$A:$D, 2, FALSE) -> 36.385 | D16: =VLOOKUP($A16, 'Medical Examinations'!$A:$D,3, FALSE) -> 7.59 | E16: =VLOOKUP($A16, 'Medical Examinations'!$A:$D, 4, FALSE) -> Yes | F16: =VLOOKUP($A16, 'Medical Examinations'!$A:$J, 5, FALSE) -> No | G16: =VLOOKUP($A16, 'Medical Examinations'!$A:$I, 6, FALSE) -> No | H16: =VLOOKUP($A16,'Medical Examinations'!$A:$L,10, FALSE) -> 2 | I16: =VLOOKUP($A16, 'Medical Examinations'!$A:$J, 9, FALSE) -> Yes | J16: =VLOOKUP($A16, 'Medical Examinations'!$A:$P, 11, FALSE) -> OBESITY | K16: 24325 | L16: =VLOOKUP($A16, 'Hospitalisation Details'!$A:$H, 7, FALSE) -> 48517.56 | M16: =VLOOKUP($A16, 'Hospitalisation Details'!$A:$L, 12, FALSE) -> tier - 1 | N16: =VLOOKUP($A16, 'Hospitalisation Details'!$A:$M, 13, FALSE) -> tier - 3 | O16: =VLOOKUP($A16, 'Hospitalisation Details'!$A:$N, 14, FALSE) -> R1024 | P16: =VLOOKUP($A16, 'Hospitalisation Details'!$A:$O, 15, FALSE) -> 61
A17: Id16 | B17: =VLOOKUP($A17,'Customer Names'!$A:$D,3, FALSE) -> Viau-Dupuis | C17: =VLOOKUP($A17,'Medical Examinations'!$A:$D, 2, FALSE) -> 39.9 | D17: =VLOOKUP($A17, 'Medical Examinations'!$A:$D,3, FALSE) -> 11.32 | E17: =VLOOKUP($A17, 'Medical Examinations'!$A:$D, 4, FALSE) -> No | F17: =VLOOKUP($A17, 'Medical Examinations'!$A:$J, 5, FALSE) -> No | G17: =VLOOKUP($A17, 'Medical Examinations'!$A:$I, 6, FALSE) -> No | H17: =VLOOKUP($A17,'Medical Examinations'!$A:$L,10, FALSE) -> 0 | I17: =VLOOKUP($A17, 'Medical Examinations'!$A:$J, 9, FALSE) -> Yes | J17: =VLOOKUP($A17, 'Medical Examinations'!$A:$P, 11, FALSE) -> OBESITY | K17: 25379 | L17: =VLOOKUP($A17, 'Hospitalisation Details'!$A:$H, 7, FALSE) -> 48173.36 | M17: =VLOOKUP($A17, 'Hospitalisation Details'!$A:$L, 12, FALSE) -> tier - 1 | N17: =VLOOKUP($A17, 'Hospitalisation Details'!$A:$M, 13, FALSE) -> tier - 3 | O17: =VLOOKUP($A17, 'Hospitalisation Details'!$A:$N, 14, FALSE) -> R1011 | P17: =VLOOKUP($A17, 'Hospitalisation Details'!$A:$O, 15, FALSE) -> 60
A18: Id17 | B18: =VLOOKUP($A18,'Customer Names'!$A:$D,3, FALSE) -> Cronin | C18: =VLOOKUP($A18,'Medical Examinations'!$A:$D, 2, FALSE) -> 33.8 | D18: =VLOOKUP($A18, 'Medical Examinations'!$A:$D,3, FALSE) -> 7.67 | E18: =VLOOKUP($A18, 'Medical Examinations'!$A:$D, 4, FALSE) -> No | F18: =VLOOKUP($A18, 'Medical Examinations'!$A:$J, 5, FALSE) -> No | G18: =VLOOKUP($A18, 'Medical Examinations'!$A:$I, 6, FALSE) -> No | H18: =VLOOKUP($A18,'Medical Examinations'!$A:$L,10, FALSE) -> 3 | I18: =VLOOKUP($A18, 'Medical Examinations'!$A:$J, 9, FALSE) -> Yes | J18: =VLOOKUP($A18, 'Medical Examinations'!$A:$P, 11, FALSE) -> OBESITY | K18: 25537 | L18: =VLOOKUP($A18, 'Hospitalisation Details'!$A:$H, 7, FALSE) -> 47928.03 | M18: =VLOOKUP($A18, 'Hospitalisation Details'!$A:$L, 12, FALSE) -> tier - 2 | N18: =VLOOKUP($A18, 'Hospitalisation Details'!$A:$M, 13, FALSE) -> tier - 3 | O18: =VLOOKUP($A18, 'Hospitalisation Details'!$A:$N, 14, FALSE) -> R1011 | P18: =VLOOKUP($A18, 'Hospitalisation Details'!$A:$O, 15, FALSE) -> 64
A19: Id18 | B19: =VLOOKUP($A19,'Customer Names'!$A:$D,3, FALSE) -> Noordstar | C19: =VLOOKUP($A19,'Medical Examinations'!$A:$D, 2, FALSE) -> 36.765 | D19: =VLOOKUP($A19, 'Medical Examinations'!$A:$D,3, FALSE) -> 7.29 | E19: =VLOOKUP($A19, 'Medical Examinations'!$A:$D, 4, FALSE) -> Yes | F19: =VLOOKUP($A19, 'Medical Examinations'!$A:$J, 5, FALSE) -> No | G19: =VLOOKUP($A19, 'Medical Examinations'!$A:$I, 6, FALSE) -> Yes | H19: =VLOOKUP($A19,'Medical Examinations'!$A:$L,10, FALSE) -> 1 | I19: =VLOOKUP($A19, 'Medical Examinations'!$A:$J, 9, FALSE) -> Yes | J19: =VLOOKUP($A19, 'Medical Examinations'!$A:$P, 11, FALSE) -> OBESITY | K19: 29453 | L19: =VLOOKUP($A19, 'Hospitalisation Details'!$A:$H, 7, FALSE) -> 47896.79 | M19: =VLOOKUP($A19, 'Hospitalisation Details'!$A:$L, 12, FALSE) -> tier - 1 | N19: =VLOOKUP($A19, 'Hospitalisation Details'!$A:$M, 13, FALSE) -> tier - 3 | O19: =VLOOKUP($A19, 'Hospitalisation Details'!$A:$N, 14, FALSE) -> R1024 | P19: =VLOOKUP($A19, 'Hospitalisation Details'!$A:$O, 15, FALSE) -> 59
A20: Id19 | B20: =VLOOKUP($A20,'Customer Names'!$A:$D,3, FALSE) -> Boudalia | C20: =VLOOKUP($A20,'Medical Examinations'!$A:$D, 2, FALSE) -> 36.955 | D20: =VLOOKUP($A20, 'Medical Examinations'!$A:$D,3, FALSE) -> 4.72 | E20: =VLOOKUP($A20, 'Medical Examinations'!$A:$D, 4, FALSE) -> Yes | F20: =VLOOKUP($A20, 'Medical Examinations'!$A:$J, 5, FALSE) -> No | G20: =VLOOKUP($A20, 'Medical Examinations'!$A:$I, 6, FALSE) -> No | H20: =VLOOKUP($A20,'Medical Examinations'!$A:$L,10, FALSE) -> 1 | I20: =VLOOKUP($A20, 'Medical Examinations'!$A:$J, 9, FALSE) -> Yes | J20: =VLOOKUP($A20, 'Medical Examinations'!$A:$P, 11, FALSE) -> OBESITY | K20: 24293 | L20: =VLOOKUP($A20, 'Hospitalisation Details'!$A:$H, 7, FALSE) -> 47496.49 | M20: =VLOOKUP($A20, 'Hospitalisation Details'!$A:$L, 12, FALSE) -> tier - 1 | N20: =VLOOKUP($A20, 'Hospitalisation Details'!$A:$M, 13, FALSE) -> tier - 3 | O20: =VLOOKUP($A20, 'Hospitalisation Details'!$A:$N, 14, FALSE) -> R1012 | P20: =VLOOKUP($A20, 'Hospitalisation Details'!$A:$O, 15, FALSE) -> 58
... A2334: Id2333 | B2334: =VLOOKUP($A2334,'Customer Names'!$A:$D,3, FALSE) -> Albano | C2334: =VLOOKUP($A2334,'Medical Examinations'!$A:$D, 2, FALSE) -> 16.47 | D2334: =VLOOKUP($A2334, 'Medical Examinations'!$A:$D,3, FALSE) -> 6.35 | E2334: =VLOOKUP($A2334, 'Medical Examinations'!$A:$D, 4, FALSE) -> No | F2334: =VLOOKUP($A2334, 'Medical Examinations'!$A:$J, 5, FALSE) -> No | G2334: =VLOOKUP($A2334, 'Medical Examinations'!$A:$I, 6, FALSE) -> Yes | H2334: =VLOOKUP($A2334,'Medical Examinations'!$A:$L,10, FALSE) -> 1 | I2334: =VLOOKUP($A2334, 'Medical Examinations'!$A:$J, 9, FALSE) -> No | J2334: =VLOOKUP($A2334, 'Medical Examinations'!$A:$P, 11, FALSE) -> UNDERWEIGHT | K2334: 22893 | L2334: =VLOOKUP($A2334, 'Hospitalisation Details'!$A:$H, 7, FALSE) -> 600 | M2334: =VLOOKUP($A2334, 'Hospitalisation Details'!$A:$L, 12, FALSE) -> tier - 2 | N2334: =VLOOKUP($A2334, 'Hospitalisation Details'!$A:$M, 13, FALSE) -> tier - 1 | O2334: =VLOOKUP($A2334, 'Hospitalisation Details'!$A:$N, 14, FALSE) -> R1013 | P2334: =VLOOKUP($A2334, 'Hospitalisation Details'!$A:$O, 15, FALSE) -> 29
A2335: Id2334 | B2335: =VLOOKUP($A2335,'Customer Names'!$A:$D,3, FALSE) -> Rosendahl | C2335: =VLOOKUP($A2335,'Medical Examinations'!$A:$D, 2, FALSE) -> 17.6 | D2335: =VLOOKUP($A2335, 'Medical Examinations'!$A:$D,3, FALSE) -> 4.39 | E2335: =VLOOKUP($A2335, 'Medical Examinations'!$A:$D, 4, FALSE) -> No | F2335: =VLOOKUP($A2335, 'Medical Examinations'!$A:$J, 5, FALSE) -> No | G2335: =VLOOKUP($A2335, 'Medical Examinations'!$A:$I, 6, FALSE) -> No | H2335: =VLOOKUP($A2335,'Medical Examinations'!$A:$L,10, FALSE) -> 1 | I2335: =VLOOKUP($A2335, 'Medical Examinations'!$A:$J, 9, FALSE) -> No | J2335: =VLOOKUP($A2335, 'Medical Examinations'!$A:$P, 11, FALSE) -> UNDERWEIGHT | K2335: 25117 | L2335: =VLOOKUP($A2335, 'Hospitalisation Details'!$A:$H, 7, FALSE) -> 570.62 | M2335: =VLOOKUP($A2335, 'Hospitalisation Details'!$A:$L, 12, FALSE) -> tier - 2 | N2335: =VLOOKUP($A2335, 'Hospitalisation Details'!$A:$M, 13, FALSE) -> tier - 1 | O2335: =VLOOKUP($A2335, '[3]Hospitalisation Details'!$A:$N, 14, FALSE) -> #REF! | P2335: =VLOOKUP($A2335, 'Hospitalisation Details'!$A:$O, 15, FALSE) -> 30

Sheet Dashboard
F1: Healthcare Dashboard

Sheet Insight Summary
A4: Insight summary
A6: Cancer History Distribution – Insights 1. A higher percentage of smokers had a history of cancer compared to non-smokers. 2. Non-smokers show a lower cancer incidence, indicating a possible risk reduction. 3. If the smoker group is significantly larger, the chart highlights the impact of smoking on cancer history. 4. The pie chart clearly shows the proportion difference between smoker and non-smoker categories. 5. This insight supports the correlation between smoking behavior and cancer probability. | B6: Findings • Smokers show significantly higher cancer cases. • Possible correlation between smoking and cancer risk.
A7: Charges by Weight Status – Insights 1. The 'Obese' weight group shows the highest average hospital charges. 2. Normal and overweight groups have moderate billing amounts. 3. Underweight patients have comparatively lower treatment charges. 4. The graph indicates that healthcare costs increase with weight category. 5. This suggests higher medical complexity or increased interventions for obese patients. | B7: • Highest charges: Obese group (₹16,591 average) • Lowest charges: Underweight (₹ 6,899average) • Charges rise as BMI category increases. • Indicates increased treatment complexity.
